[
  {
    "blue_key": 764,
    "red_key": 774,
    "rounds": 500,
    "blue_tiles": 5,
    "red_tiles": 1,
    "blue_troops": 82,
    "red_troops": 3,
    "blue_production_moves": 187,
    "red_production_moves": 108,
    "blue_attack_moves": 4,
    "red_attack_moves": 304,
    "blue_transport_moves": 309,
    "red_transport_moves": 87,
    "blue_guided_moves": 313,
    "red_guided_moves": 391,
    "blue_fitness": 11.949999999999884,
    "red_fitness": 21.66999999999991,
    "winner": "Tie"
  },
  {
    "blue_key": 778,
    "red_key": 739,
    "rounds": 500,
    "blue_tiles": 3,
    "red_tiles": 4,
    "blue_troops": 50,
    "red_troops": 50,
    "blue_production_moves": 111,
    "red_production_moves": 111,
    "blue_attack_moves": 202,
    "red_attack_moves": 332,
    "blue_transport_moves": 187,
    "red_transport_moves": 56,
    "blue_guided_moves": 431,
    "red_guided_moves": 395,
    "blue_fitness": 11.549999999999894,
    "red_fitness": 14.81999999999991,
    "winner": "Tie"
  },
  {
    "blue_key": 759,
    "red_key": 675,
    "rounds": 500,
    "blue_tiles": 9,
    "red_tiles": 2,
    "blue_troops": 152,
    "red_troops": 20,
    "blue_production_moves": 151,
    "red_production_moves": 19,
    "blue_attack_moves": 10,
    "red_attack_moves": 242,
    "blue_transport_moves": 339,
    "red_transport_moves": 238,
    "blue_guided_moves": 349,
    "red_guided_moves": 499,
    "blue_fitness": 11.669999999999872,
    "red_fitness": 12.569999999999883,
    "winner": "Tie"
  },
  {
    "blue_key": 610,
    "red_key": 768,
    "rounds": 500,
    "blue_tiles": 9,
    "red_tiles": 6,
    "blue_troops": 138,
    "red_troops": 109,
    "blue_production_moves": 137,
    "red_production_moves": 108,
    "blue_attack_moves": 42,
    "red_attack_moves": 6,
    "blue_transport_moves": 321,
    "red_transport_moves": 385,
    "blue_guided_moves": 363,
    "red_guided_moves": 476,
    "blue_fitness": 11.689999999999879,
    "red_fitness": 11.159999999999881,
    "winner": "Tie"
  },
  {
    "blue_key": 768,
    "red_key": 779,
    "rounds": 500,
    "blue_tiles": 7,
    "red_tiles": 11,
    "blue_troops": 130,
    "red_troops": 163,
    "blue_production_moves": 150,
    "red_production_moves": 183,
    "blue_attack_moves": 17,
    "red_attack_moves": 95,
    "blue_transport_moves": 333,
    "red_transport_moves": 221,
    "blue_guided_moves": 445,
    "red_guided_moves": 337,
    "blue_fitness": 11.619999999999878,
    "red_fitness": 14.079999999999878,
    "winner": "Tie"
  },
  {
    "blue_key": 668,
    "red_key": 778,
    "rounds": 500,
    "blue_tiles": 12,
    "red_tiles": 10,
    "blue_troops": 148,
    "red_troops": 184,
    "blue_production_moves": 147,
    "red_production_moves": 183,
    "blue_attack_moves": 22,
    "red_attack_moves": 10,
    "blue_transport_moves": 331,
    "red_transport_moves": 306,
    "blue_guided_moves": 354,
    "red_guided_moves": 316,
    "blue_fitness": 11.689999999999879,
    "red_fitness": 11.989999999999863,
    "winner": "Tie"
  },
  {
    "blue_key": 693,
    "red_key": 786,
    "rounds": 500,
    "blue_tiles": 8,
    "red_tiles": 16,
    "blue_troops": 140,
    "red_troops": 170,
    "blue_production_moves": 149,
    "red_production_moves": 179,
    "blue_attack_moves": 8,
    "red_attack_moves": 74,
    "blue_transport_moves": 343,
    "red_transport_moves": 246,
    "blue_guided_moves": 448,
    "red_guided_moves": 330,
    "blue_fitness": 11.62999999999988,
    "red_fitness": 12.73999999999987,
    "winner": "Tie"
  },
  {
    "blue_key": 774,
    "red_key": 784,
    "rounds": 500,
    "blue_tiles": 8,
    "red_tiles": 11,
    "blue_troops": 152,
    "red_troops": 145,
    "blue_production_moves": 155,
    "red_production_moves": 148,
    "blue_attack_moves": 7,
    "red_attack_moves": 38,
    "blue_transport_moves": 338,
    "red_transport_moves": 313,
    "blue_guided_moves": 345,
    "red_guided_moves": 353,
    "blue_fitness": 11.68999999999988,
    "red_fitness": 12.029999999999868,
    "winner": "Tie"
  },
  {
    "blue_key": 753,
    "red_key": 763,
    "rounds": 500,
    "blue_tiles": 9,
    "red_tiles": 12,
    "blue_troops": 143,
    "red_troops": 205,
    "blue_production_moves": 142,
    "red_production_moves": 204,
    "blue_attack_moves": 49,
    "red_attack_moves": 15,
    "blue_transport_moves": 309,
    "red_transport_moves": 280,
    "blue_guided_moves": 497,
    "red_guided_moves": 305,
    "blue_fitness": 11.639999999999871,
    "red_fitness": 12.239999999999856,
    "winner": "Tie"
  },
  {
    "blue_key": 779,
    "red_key": 789,
    "rounds": 500,
    "blue_tiles": 8,
    "red_tiles": 4,
    "blue_troops": 153,
    "red_troops": 41,
    "blue_production_moves": 152,
    "red_production_moves": 40,
    "blue_attack_moves": 7,
    "red_attack_moves": 126,
    "blue_transport_moves": 341,
    "red_transport_moves": 333,
    "blue_guided_moves": 381,
    "red_guided_moves": 499,
    "blue_fitness": 11.65999999999988,
    "red_fitness": 11.659999999999869,
    "winner": "Tie"
  },
  {
    "blue_key": 776,
    "red_key": 787,
    "rounds": 500,
    "blue_tiles": 3,
    "red_tiles": 5,
    "blue_troops": 53,
    "red_troops": 35,
    "blue_production_moves": 190,
    "red_production_moves": 172,
    "blue_attack_moves": 48,
    "red_attack_moves": 260,
    "blue_transport_moves": 262,
    "red_transport_moves": 67,
    "blue_guided_moves": 310,
    "red_guided_moves": 327,
    "blue_fitness": 21.8299999999999,
    "red_fitness": 16.199999999999864,
    "winner": "Tie"
  },
  {
    "blue_key": 510,
    "red_key": 800,
    "rounds": 500,
    "blue_tiles": 12,
    "red_tiles": 10,
    "blue_troops": 177,
    "red_troops": 155,
    "blue_production_moves": 183,
    "red_production_moves": 161,
    "blue_attack_moves": 41,
    "red_attack_moves": 20,
    "blue_transport_moves": 276,
    "red_transport_moves": 318,
    "blue_guided_moves": 321,
    "red_guided_moves": 338,
    "blue_fitness": 13.079999999999867,
    "red_fitness": 11.769999999999873,
    "winner": "Tie"
  },
  {
    "blue_key": 771,
    "red_key": 781,
    "rounds": 500,
    "blue_tiles": 9,
    "red_tiles": 16,
    "blue_troops": 177,
    "red_troops": 195,
    "blue_production_moves": 187,
    "red_production_moves": 205,
    "blue_attack_moves": 29,
    "red_attack_moves": 43,
    "blue_transport_moves": 284,
    "red_transport_moves": 251,
    "blue_guided_moves": 313,
    "red_guided_moves": 396,
    "blue_fitness": 14.629999999999868,
    "red_fitness": 12.789999999999875,
    "winner": "Tie"
  },
  {
    "blue_key": 794,
    "red_key": 805,
    "rounds": 500,
    "blue_tiles": 9,
    "red_tiles": 10,
    "blue_troops": 149,
    "red_troops": 184,
    "blue_production_moves": 148,
    "red_production_moves": 183,
    "blue_attack_moves": 8,
    "red_attack_moves": 10,
    "blue_transport_moves": 344,
    "red_transport_moves": 306,
    "blue_guided_moves": 365,
    "red_guided_moves": 316,
    "blue_fitness": 11.63999999999988,
    "red_fitness": 11.989999999999863,
    "winner": "Tie"
  },
  {
    "blue_key": 738,
    "red_key": 790,
    "rounds": 500,
    "blue_tiles": 7,
    "red_tiles": 17,
    "blue_troops": 71,
    "red_troops": 91,
    "blue_production_moves": 173,
    "red_production_moves": 193,
    "blue_attack_moves": 104,
    "red_attack_moves": 297,
    "blue_transport_moves": 223,
    "red_transport_moves": 9,
    "blue_guided_moves": 335,
    "red_guided_moves": 328,
    "blue_fitness": 19.399999999999885,
    "red_fitness": 21.510000000000034,
    "winner": "Tie"
  },
  {
    "blue_key": 797,
    "red_key": 808,
    "rounds": 500,
    "blue_tiles": 8,
    "red_tiles": 11,
    "blue_troops": 82,
    "red_troops": 132,
    "blue_production_moves": 183,
    "red_production_moves": 233,
    "blue_attack_moves": 262,
    "red_attack_moves": 118,
    "blue_transport_moves": 55,
    "red_transport_moves": 148,
    "blue_guided_moves": 357,
    "red_guided_moves": 276,
    "blue_fitness": 17.569999999999904,
    "red_fitness": 15.639999999999844,
    "winner": "Tie"
  },
  {
    "blue_key": 807,
    "red_key": 818,
    "rounds": 500,
    "blue_tiles": 5,
    "red_tiles": 7,
    "blue_troops": 63,
    "red_troops": 33,
    "blue_production_moves": 145,
    "red_production_moves": 115,
    "blue_attack_moves": 193,
    "red_attack_moves": 333,
    "blue_transport_moves": 162,
    "red_transport_moves": 51,
    "blue_guided_moves": 357,
    "red_guided_moves": 393,
    "blue_fitness": 13.649999999999904,
    "red_fitness": 25.569999999999904,
    "winner": "Tie"
  },
  {
    "blue_key": 803,
    "red_key": 813,
    "rounds": 500,
    "blue_tiles": 5,
    "red_tiles": 10,
    "blue_troops": 84,
    "red_troops": 43,
    "blue_production_moves": 143,
    "red_production_moves": 102,
    "blue_attack_moves": 4,
    "red_attack_moves": 391,
    "blue_transport_moves": 353,
    "red_transport_moves": 6,
    "blue_guided_moves": 357,
    "red_guided_moves": 414,
    "blue_fitness": 11.509999999999874,
    "red_fitness": 18.769999999999936,
    "winner": "Tie"
  },
  {
    "blue_key": 813,
    "red_key": 823,
    "rounds": 500,
    "blue_tiles": 7,
    "red_tiles": 8,
    "blue_troops": 106,
    "red_troops": 149,
    "blue_production_moves": 142,
    "red_production_moves": 185,
    "blue_attack_moves": 175,
    "red_attack_moves": 12,
    "blue_transport_moves": 183,
    "red_transport_moves": 302,
    "blue_guided_moves": 366,
    "red_guided_moves": 314,
    "blue_fitness": 13.2099999999999,
    "red_fitness": 13.039999999999866,
    "winner": "Tie"
  },
  {
    "blue_key": 777,
    "red_key": 788,
    "rounds": 500,
    "blue_tiles": 9,
    "red_tiles": 8,
    "blue_troops": 153,
    "red_troops": 149,
    "blue_production_moves": 172,
    "red_production_moves": 168,
    "blue_attack_moves": 13,
    "red_attack_moves": 15,
    "blue_transport_moves": 315,
    "red_transport_moves": 316,
    "blue_guided_moves": 328,
    "red_guided_moves": 331,
    "blue_fitness": 12.689999999999875,
    "red_fitness": 11.829999999999872,
    "winner": "Tie"
  },
  {
    "blue_key": 772,
    "red_key": 782,
    "rounds": 500,
    "blue_tiles": 9,
    "red_tiles": 10,
    "blue_troops": 160,
    "red_troops": 184,
    "blue_production_moves": 159,
    "red_production_moves": 183,
    "blue_attack_moves": 12,
    "red_attack_moves": 10,
    "blue_transport_moves": 329,
    "red_transport_moves": 306,
    "blue_guided_moves": 410,
    "red_guided_moves": 316,
    "blue_fitness": 11.749999999999877,
    "red_fitness": 11.989999999999863,
    "winner": "Tie"
  },
  {
    "blue_key": 790,
    "red_key": 801,
    "rounds": 500,
    "blue_tiles": 19,
    "red_tiles": 7,
    "blue_troops": 291,
    "red_troops": 132,
    "blue_production_moves": 290,
    "red_production_moves": 131,
    "blue_attack_moves": 81,
    "red_attack_moves": 91,
    "blue_transport_moves": 129,
    "red_transport_moves": 277,
    "blue_guided_moves": 240,
    "red_guided_moves": 369,
    "blue_fitness": 13.259999999999893,
    "red_fitness": 11.419999999999877,
    "winner": "Tie"
  },
  {
    "blue_key": 824,
    "red_key": 725,
    "rounds": 500,
    "blue_tiles": 13,
    "red_tiles": 8,
    "blue_troops": 101,
    "red_troops": 64,
    "blue_production_moves": 231,
    "red_production_moves": 194,
    "blue_attack_moves": 247,
    "red_attack_moves": 274,
    "blue_transport_moves": 22,
    "red_transport_moves": 31,
    "blue_guided_moves": 324,
    "red_guided_moves": 349,
    "blue_fitness": 23.90999999999995,
    "red_fitness": 38.27000000000007,
    "winner": "Tie"
  },
  {
    "blue_key": 815,
    "red_key": 826,
    "rounds": 500,
    "blue_tiles": 14,
    "red_tiles": 9,
    "blue_troops": 145,
    "red_troops": 128,
    "blue_production_moves": 206,
    "red_production_moves": 189,
    "blue_attack_moves": 127,
    "red_attack_moves": 29,
    "blue_transport_moves": 167,
    "red_transport_moves": 281,
    "blue_guided_moves": 357,
    "red_guided_moves": 324,
    "blue_fitness": 22.189999999999856,
    "red_fitness": 12.089999999999858,
    "winner": "Tie"
  },
  {
    "blue_key": 827,
    "red_key": 837,
    "rounds": 500,
    "blue_tiles": 15,
    "red_tiles": 5,
    "blue_troops": 137,
    "red_troops": 59,
    "blue_production_moves": 219,
    "red_production_moves": 141,
    "blue_attack_moves": 172,
    "red_attack_moves": 246,
    "blue_transport_moves": 109,
    "red_transport_moves": 112,
    "blue_guided_moves": 307,
    "red_guided_moves": 363,
    "blue_fitness": 17.789999999999953,
    "red_fitness": 15.639999999999931,
    "winner": "Tie"
  },
  {
    "blue_key": 834,
    "red_key": 844,
    "rounds": 500,
    "blue_tiles": 8,
    "red_tiles": 6,
    "blue_troops": 141,
    "red_troops": 112,
    "blue_production_moves": 140,
    "red_production_moves": 111,
    "blue_attack_moves": 7,
    "red_attack_moves": 154,
    "blue_transport_moves": 353,
    "red_transport_moves": 234,
    "blue_guided_moves": 360,
    "red_guided_moves": 446,
    "blue_fitness": 11.539999999999871,
    "red_fitness": 11.649999999999897,
    "winner": "Tie"
  },
  {
    "blue_key": 814,
    "red_key": 824,
    "rounds": 500,
    "blue_tiles": 12,
    "red_tiles": 7,
    "blue_troops": 121,
    "red_troops": 116,
    "blue_production_moves": 204,
    "red_production_moves": 199,
    "blue_attack_moves": 74,
    "red_attack_moves": 83,
    "blue_transport_moves": 222,
    "red_transport_moves": 217,
    "blue_guided_moves": 299,
    "red_guided_moves": 310,
    "blue_fitness": 13.299999999999875,
    "red_fitness": 26.159999999999982,
    "winner": "Tie"
  },
  {
    "blue_key": 808,
    "red_key": 819,
    "rounds": 500,
    "blue_tiles": 6,
    "red_tiles": 14,
    "blue_troops": 91,
    "red_troops": 231,
    "blue_production_moves": 123,
    "red_production_moves": 263,
    "blue_attack_moves": 85,
    "red_attack_moves": 100,
    "blue_transport_moves": 292,
    "red_transport_moves": 136,
    "blue_guided_moves": 377,
    "red_guided_moves": 258,
    "blue_fitness": 11.85999999999988,
    "red_fitness": 17.58999999999991,
    "winner": "Tie"
  },
  {
    "blue_key": 829,
    "red_key": 839,
    "rounds": 500,
    "blue_tiles": 11,
    "red_tiles": 10,
    "blue_troops": 217,
    "red_troops": 184,
    "blue_production_moves": 216,
    "red_production_moves": 183,
    "blue_attack_moves": 17,
    "red_attack_moves": 10,
    "blue_transport_moves": 267,
    "red_transport_moves": 306,
    "blue_guided_moves": 310,
    "red_guided_moves": 316,
    "blue_fitness": 12.35999999999988,
    "red_fitness": 11.989999999999863,
    "winner": "Tie"
  },
  {
    "blue_key": 825,
    "red_key": 834,
    "rounds": 500,
    "blue_tiles": 5,
    "red_tiles": 16,
    "blue_troops": 41,
    "red_troops": 195,
    "blue_production_moves": 123,
    "red_production_moves": 277,
    "blue_attack_moves": 298,
    "red_attack_moves": 54,
    "blue_transport_moves": 79,
    "red_transport_moves": 168,
    "blue_guided_moves": 384,
    "red_guided_moves": 251,
    "blue_fitness": 25.379999999999928,
    "red_fitness": 14.629999999999885,
    "winner": "Tie"
  },
  {
    "blue_key": 816,
    "red_key": 717,
    "rounds": 500,
    "blue_tiles": 8,
    "red_tiles": 8,
    "blue_troops": 113,
    "red_troops": 139,
    "blue_production_moves": 117,
    "red_production_moves": 143,
    "blue_attack_moves": 88,
    "red_attack_moves": 83,
    "blue_transport_moves": 295,
    "red_transport_moves": 273,
    "blue_guided_moves": 383,
    "red_guided_moves": 357,
    "blue_fitness": 11.609999999999872,
    "red_fitness": 13.049999999999871,
    "winner": "Tie"
  },
  {
    "blue_key": 835,
    "red_key": 845,
    "rounds": 500,
    "blue_tiles": 9,
    "red_tiles": 9,
    "blue_troops": 146,
    "red_troops": 172,
    "blue_production_moves": 175,
    "red_production_moves": 201,
    "blue_attack_moves": 99,
    "red_attack_moves": 21,
    "blue_transport_moves": 226,
    "red_transport_moves": 277,
    "blue_guided_moves": 333,
    "red_guided_moves": 298,
    "blue_fitness": 13.979999999999865,
    "red_fitness": 16.659999999999865,
    "winner": "Tie"
  },
  {
    "blue_key": 588,
    "red_key": 825,
    "rounds": 500,
    "blue_tiles": 14,
    "red_tiles": 5,
    "blue_troops": 137,
    "red_troops": 95,
    "blue_production_moves": 279,
    "red_production_moves": 237,
    "blue_attack_moves": 179,
    "red_attack_moves": 6,
    "blue_transport_moves": 42,
    "red_transport_moves": 256,
    "blue_guided_moves": 258,
    "red_guided_moves": 262,
    "blue_fitness": 43.340000000000146,
    "red_fitness": 12.449999999999891,
    "winner": "Tie"
  },
  {
    "blue_key": 627,
    "red_key": 783,
    "rounds": 500,
    "blue_tiles": 15,
    "red_tiles": 12,
    "blue_troops": 185,
    "red_troops": 180,
    "blue_production_moves": 200,
    "red_production_moves": 195,
    "blue_attack_moves": 35,
    "red_attack_moves": 89,
    "blue_transport_moves": 265,
    "red_transport_moves": 215,
    "blue_guided_moves": 324,
    "red_guided_moves": 401,
    "blue_fitness": 14.989999999999874,
    "red_fitness": 13.009999999999872,
    "winner": "Tie"
  },
  {
    "blue_key": 633,
    "red_key": 835,
    "rounds": 500,
    "blue_tiles": 3,
    "red_tiles": 16,
    "blue_troops": 26,
    "red_troops": 90,
    "blue_production_moves": 106,
    "red_production_moves": 170,
    "blue_attack_moves": 372,
    "red_attack_moves": 71,
    "blue_transport_moves": 22,
    "red_transport_moves": 258,
    "blue_guided_moves": 394,
    "red_guided_moves": 366,
    "blue_fitness": 16.259999999999895,
    "red_fitness": 12.619999999999871,
    "winner": "Tie"
  },
  {
    "blue_key": 836,
    "red_key": 817,
    "rounds": 500,
    "blue_tiles": 9,
    "red_tiles": 14,
    "blue_troops": 161,
    "red_troops": 168,
    "blue_production_moves": 187,
    "red_production_moves": 194,
    "blue_attack_moves": 37,
    "red_attack_moves": 77,
    "blue_transport_moves": 276,
    "red_transport_moves": 228,
    "blue_guided_moves": 314,
    "red_guided_moves": 307,
    "blue_fitness": 13.539999999999846,
    "red_fitness": 13.67999999999985,
    "winner": "Tie"
  },
  {
    "blue_key": 784,
    "red_key": 795,
    "rounds": 493,
    "blue_tiles": 9,
    "red_tiles": 9,
    "blue_troops": 121,
    "red_troops": 140,
    "blue_production_moves": 141,
    "red_production_moves": 160,
    "blue_attack_moves": 10,
    "red_attack_moves": 110,
    "blue_transport_moves": 342,
    "red_transport_moves": 223,
    "blue_guided_moves": 406,
    "red_guided_moves": 352,
    "blue_fitness": 11.449999999999893,
    "red_fitness": 13.579999999999885,
    "winner": "Tie"
  },
  {
    "blue_key": 819,
    "red_key": 829,
    "rounds": 442,
    "blue_tiles": 19,
    "red_tiles": 6,
    "blue_troops": 175,
    "red_troops": 117,
    "blue_production_moves": 217,
    "red_production_moves": 159,
    "blue_attack_moves": 78,
    "red_attack_moves": 24,
    "blue_transport_moves": 147,
    "red_transport_moves": 258,
    "blue_guided_moves": 241,
    "red_guided_moves": 282,
    "blue_fitness": 19.379999999999924,
    "red_fitness": 12.039999999999898,
    "winner": "Tie"
  },
  {
    "blue_key": 765,
    "red_key": 775,
    "rounds": 378,
    "blue_tiles": 0,
    "red_tiles": 7,
    "blue_troops": 0,
    "red_troops": 123,
    "blue_production_moves": 1,
    "red_production_moves": 124,
    "blue_attack_moves": 374,
    "red_attack_moves": 14,
    "blue_transport_moves": 3,
    "red_transport_moves": 239,
    "blue_guided_moves": 378,
    "red_guided_moves": 253,
    "blue_fitness": 7.6799999999999295,
    "red_fitness": 8.899999999999936,
    "winner": "Red"
  },
  {
    "blue_key": 783,
    "red_key": 794,
    "rounds": 304,
    "blue_tiles": 15,
    "red_tiles": 2,
    "blue_troops": 150,
    "red_troops": 14,
    "blue_production_moves": 199,
    "red_production_moves": 63,
    "blue_attack_moves": 57,
    "red_attack_moves": 233,
    "blue_transport_moves": 48,
    "red_transport_moves": 7,
    "blue_guided_moves": 114,
    "red_guided_moves": 241,
    "blue_fitness": 12.06999999999991,
    "red_fitness": 10.019999999999937,
    "winner": "Tie"
  },
  {
    "blue_key": 802,
    "red_key": 812,
    "rounds": 292,
    "blue_tiles": 6,
    "red_tiles": 6,
    "blue_troops": 58,
    "red_troops": 103,
    "blue_production_moves": 105,
    "red_production_moves": 150,
    "blue_attack_moves": 130,
    "red_attack_moves": 10,
    "blue_transport_moves": 57,
    "red_transport_moves": 131,
    "blue_guided_moves": 234,
    "red_guided_moves": 141,
    "blue_fitness": 14.499999999999972,
    "red_fitness": 7.41999999999998,
    "winner": "Tie"
  },
  {
    "blue_key": 800,
    "red_key": 691,
    "rounds": 262,
    "blue_tiles": 0,
    "red_tiles": 5,
    "blue_troops": 0,
    "red_troops": 35,
    "blue_production_moves": 88,
    "red_production_moves": 123,
    "blue_attack_moves": 123,
    "red_attack_moves": 113,
    "blue_transport_moves": 51,
    "red_transport_moves": 25,
    "blue_guided_moves": 183,
    "red_guided_moves": 143,
    "blue_fitness": 15.349999999999989,
    "red_fitness": 13.07999999999996,
    "winner": "Red"
  },
  {
    "blue_key": 811,
    "red_key": 821,
    "rounds": 257,
    "blue_tiles": 7,
    "red_tiles": 3,
    "blue_troops": 127,
    "red_troops": 42,
    "blue_production_moves": 126,
    "red_production_moves": 41,
    "blue_attack_moves": 6,
    "red_attack_moves": 130,
    "blue_transport_moves": 125,
    "red_transport_moves": 85,
    "blue_guided_moves": 131,
    "red_guided_moves": 251,
    "blue_fitness": 6.51999999999997,
    "red_fitness": 6.219999999999965,
    "winner": "Tie"
  },
  {
    "blue_key": 773,
    "red_key": 749,
    "rounds": 231,
    "blue_tiles": 3,
    "red_tiles": 6,
    "blue_troops": 58,
    "red_troops": 37,
    "blue_production_moves": 97,
    "red_production_moves": 76,
    "blue_attack_moves": 3,
    "red_attack_moves": 155,
    "blue_transport_moves": 131,
    "red_transport_moves": 0,
    "blue_guided_moves": 134,
    "red_guided_moves": 182,
    "blue_fitness": 6.03999999999998,
    "red_fitness": 7.449999999999983,
    "winner": "Tie"
  },
  {
    "blue_key": 780,
    "red_key": 791,
    "rounds": 221,
    "blue_tiles": 5,
    "red_tiles": 9,
    "blue_troops": 93,
    "red_troops": 107,
    "blue_production_moves": 96,
    "red_production_moves": 110,
    "blue_attack_moves": 4,
    "red_attack_moves": 33,
    "blue_transport_moves": 121,
    "red_transport_moves": 77,
    "blue_guided_moves": 125,
    "red_guided_moves": 120,
    "blue_fitness": 5.459999999999978,
    "red_fitness": 6.429999999999996,
    "winner": "Tie"
  },
  {
    "blue_key": 823,
    "red_key": 833,
    "rounds": 220,
    "blue_tiles": 16,
    "red_tiles": 4,
    "blue_troops": 81,
    "red_troops": 24,
    "blue_production_moves": 117,
    "red_production_moves": 60,
    "blue_attack_moves": 92,
    "red_attack_moves": 121,
    "blue_transport_moves": 11,
    "red_transport_moves": 39,
    "blue_guided_moves": 146,
    "red_guided_moves": 200,
    "blue_fitness": 8.629999999999974,
    "red_fitness": 8.219999999999986,
    "winner": "Tie"
  },
  {
    "blue_key": 821,
    "red_key": 831,
    "rounds": 219,
    "blue_tiles": 4,
    "red_tiles": 1,
    "blue_troops": 35,
    "red_troops": 2,
    "blue_production_moves": 113,
    "red_production_moves": 80,
    "blue_attack_moves": 104,
    "red_attack_moves": 77,
    "blue_transport_moves": 2,
    "red_transport_moves": 62,
    "blue_guided_moves": 106,
    "red_guided_moves": 219,
    "blue_fitness": 19.379999999999953,
    "red_fitness": 5.799999999999993,
    "winner": "Tie"
  },
  {
    "blue_key": 805,
    "red_key": 816,
    "rounds": 217,
    "blue_tiles": 0,
    "red_tiles": 4,
    "blue_troops": 0,
    "red_troops": 73,
    "blue_production_moves": 65,
    "red_production_moves": 138,
    "blue_attack_moves": 147,
    "red_attack_moves": 4,
    "blue_transport_moves": 5,
    "red_transport_moves": 74,
    "blue_guided_moves": 170,
    "red_guided_moves": 78,
    "blue_fitness": 17.15,
    "red_fitness": 5.759999999999993,
    "winner": "Red"
  },
  {
    "blue_key": 832,
    "red_key": 842,
    "rounds": 174,
    "blue_tiles": 9,
    "red_tiles": 5,
    "blue_troops": 113,
    "red_troops": 97,
    "blue_production_moves": 115,
    "red_production_moves": 99,
    "blue_attack_moves": 38,
    "red_attack_moves": 5,
    "blue_transport_moves": 21,
    "red_transport_moves": 69,
    "blue_guided_moves": 72,
    "red_guided_moves": 81,
    "blue_fitness": 4.9399999999999995,
    "red_fitness": 4.52999999999999,
    "winner": "Tie"
  },
  {
    "blue_key": 830,
    "red_key": 840,
    "rounds": 170,
    "blue_tiles": 5,
    "red_tiles": 7,
    "blue_troops": 52,
    "red_troops": 39,
    "blue_production_moves": 69,
    "red_production_moves": 56,
    "blue_attack_moves": 59,
    "red_attack_moves": 109,
    "blue_transport_moves": 42,
    "red_transport_moves": 4,
    "blue_guided_moves": 107,
    "red_guided_moves": 127,
    "blue_fitness": 9.539999999999997,
    "red_fitness": 5.479999999999991,
    "winner": "Tie"
  },
  {
    "blue_key": 786,
    "red_key": 797,
    "rounds": 164,
    "blue_tiles": 3,
    "red_tiles": 0,
    "blue_troops": 51,
    "red_troops": 0,
    "blue_production_moves": 76,
    "red_production_moves": 25,
    "blue_attack_moves": 6,
    "red_attack_moves": 134,
    "blue_transport_moves": 82,
    "red_transport_moves": 5,
    "blue_guided_moves": 88,
    "red_guided_moves": 139,
    "blue_fitness": 4.9399999999999915,
    "red_fitness": 5.889999999999982,
    "winner": "Blue"
  },
  {
    "blue_key": 766,
    "red_key": 776,
    "rounds": 158,
    "blue_tiles": 0,
    "red_tiles": 5,
    "blue_troops": 0,
    "red_troops": 35,
    "blue_production_moves": 46,
    "red_production_moves": 81,
    "blue_attack_moves": 88,
    "red_attack_moves": 41,
    "blue_transport_moves": 24,
    "red_transport_moves": 35,
    "blue_guided_moves": 112,
    "red_guided_moves": 99,
    "blue_fitness": 7.259999999999978,
    "red_fitness": 4.809999999999994,
    "winner": "Red"
  },
  {
    "blue_key": 796,
    "red_key": 807,
    "rounds": 120,
    "blue_tiles": 3,
    "red_tiles": 0,
    "blue_troops": 41,
    "red_troops": 0,
    "blue_production_moves": 66,
    "red_production_moves": 25,
    "blue_attack_moves": 9,
    "red_attack_moves": 93,
    "blue_transport_moves": 45,
    "red_transport_moves": 2,
    "blue_guided_moves": 55,
    "red_guided_moves": 95,
    "blue_fitness": 5.189999999999997,
    "red_fitness": 4.279999999999999,
    "winner": "Blue"
  },
  {
    "blue_key": 754,
    "red_key": 711,
    "rounds": 116,
    "blue_tiles": 0,
    "red_tiles": 3,
    "blue_troops": 0,
    "red_troops": 58,
    "blue_production_moves": 6,
    "red_production_moves": 64,
    "blue_attack_moves": 94,
    "red_attack_moves": 8,
    "blue_transport_moves": 16,
    "red_transport_moves": 43,
    "blue_guided_moves": 116,
    "red_guided_moves": 115,
    "blue_fitness": 2.6900000000000004,
    "red_fitness": 4.079999999999999,
    "winner": "Red"
  },
  {
    "blue_key": 756,
    "red_key": 766,
    "rounds": 109,
    "blue_tiles": 0,
    "red_tiles": 4,
    "blue_troops": 0,
    "red_troops": 61,
    "blue_production_moves": 1,
    "red_production_moves": 62,
    "blue_attack_moves": 94,
    "red_attack_moves": 4,
    "blue_transport_moves": 14,
    "red_transport_moves": 42,
    "blue_guided_moves": 109,
    "red_guided_moves": 108,
    "blue_fitness": 2.3700000000000014,
    "red_fitness": 2.839999999999999,
    "winner": "Red"
  },
  {
    "blue_key": 639,
    "red_key": 804,
    "rounds": 86,
    "blue_tiles": 4,
    "red_tiles": 0,
    "blue_troops": 43,
    "red_troops": 0,
    "blue_production_moves": 53,
    "red_production_moves": 10,
    "blue_attack_moves": 4,
    "red_attack_moves": 75,
    "blue_transport_moves": 29,
    "red_transport_moves": 1,
    "blue_guided_moves": 78,
    "red_guided_moves": 77,
    "blue_fitness": 2.3100000000000005,
    "red_fitness": 2.3600000000000008,
    "winner": "Blue"
  },
  {
    "blue_key": 752,
    "red_key": 669,
    "rounds": 76,
    "blue_tiles": 2,
    "red_tiles": 8,
    "blue_troops": 30,
    "red_troops": 35,
    "blue_production_moves": 43,
    "red_production_moves": 48,
    "blue_attack_moves": 20,
    "red_attack_moves": 27,
    "blue_transport_moves": 13,
    "red_transport_moves": 1,
    "blue_guided_moves": 44,
    "red_guided_moves": 35,
    "blue_fitness": 3.529999999999994,
    "red_fitness": 3.8699999999999966,
    "winner": "Tie"
  },
  {
    "blue_key": 788,
    "red_key": 798,
    "rounds": 70,
    "blue_tiles": 0,
    "red_tiles": 10,
    "blue_troops": 0,
    "red_troops": 29,
    "blue_production_moves": 10,
    "red_production_moves": 39,
    "blue_attack_moves": 60,
    "red_attack_moves": 30,
    "blue_transport_moves": 0,
    "red_transport_moves": 0,
    "blue_guided_moves": 67,
    "red_guided_moves": 30,
    "blue_fitness": 3.4500000000000006,
    "red_fitness": 1.9700000000000015,
    "winner": "Red"
  },
  {
    "blue_key": 817,
    "red_key": 827,
    "rounds": 70,
    "blue_tiles": 6,
    "red_tiles": 0,
    "blue_troops": 54,
    "red_troops": 0,
    "blue_production_moves": 55,
    "red_production_moves": 1,
    "blue_attack_moves": 10,
    "red_attack_moves": 69,
    "blue_transport_moves": 5,
    "red_transport_moves": 0,
    "blue_guided_moves": 15,
    "red_guided_moves": 70,
    "blue_fitness": 2.050000000000001,
    "red_fitness": 1.4500000000000008,
    "winner": "Blue"
  },
  {
    "blue_key": 793,
    "red_key": 803,
    "rounds": 48,
    "blue_tiles": 3,
    "red_tiles": 0,
    "blue_troops": 27,
    "red_troops": 0,
    "blue_production_moves": 30,
    "red_production_moves": 3,
    "blue_attack_moves": 9,
    "red_attack_moves": 43,
    "blue_transport_moves": 9,
    "red_transport_moves": 2,
    "blue_guided_moves": 18,
    "red_guided_moves": 48,
    "blue_fitness": 1.300000000000001,
    "red_fitness": 1.1400000000000006,
    "winner": "Blue"
  },
  {
    "blue_key": 767,
    "red_key": 777,
    "rounds": 46,
    "blue_tiles": 0,
    "red_tiles": 3,
    "blue_troops": 0,
    "red_troops": 25,
    "blue_production_moves": 10,
    "red_production_moves": 35,
    "blue_attack_moves": 27,
    "red_attack_moves": 10,
    "blue_transport_moves": 9,
    "red_transport_moves": 0,
    "blue_guided_moves": 46,
    "red_guided_moves": 10,
    "blue_fitness": 1.8600000000000005,
    "red_fitness": 2.39,
    "winner": "Red"
  },
  {
    "blue_key": 801,
    "red_key": 811,
    "rounds": 42,
    "blue_tiles": 2,
    "red_tiles": 5,
    "blue_troops": 28,
    "red_troops": 10,
    "blue_production_moves": 30,
    "red_production_moves": 12,
    "blue_attack_moves": 1,
    "red_attack_moves": 30,
    "blue_transport_moves": 11,
    "red_transport_moves": 0,
    "blue_guided_moves": 12,
    "red_guided_moves": 35,
    "blue_fitness": 1.1600000000000008,
    "red_fitness": 1.7000000000000006,
    "winner": "Tie"
  },
  {
    "blue_key": 822,
    "red_key": 832,
    "rounds": 41,
    "blue_tiles": 5,
    "red_tiles": 4,
    "blue_troops": 25,
    "red_troops": 9,
    "blue_production_moves": 25,
    "red_production_moves": 9,
    "blue_attack_moves": 16,
    "red_attack_moves": 15,
    "blue_transport_moves": 0,
    "red_transport_moves": 16,
    "blue_guided_moves": 16,
    "red_guided_moves": 40,
    "blue_fitness": 1.3700000000000006,
    "red_fitness": 0.9800000000000004,
    "winner": "Tie"
  },
  {
    "blue_key": 762,
    "red_key": 746,
    "rounds": 39,
    "blue_tiles": 2,
    "red_tiles": 4,
    "blue_troops": 20,
    "red_troops": 7,
    "blue_production_moves": 19,
    "red_production_moves": 6,
    "blue_attack_moves": 14,
    "red_attack_moves": 27,
    "blue_transport_moves": 6,
    "red_transport_moves": 6,
    "blue_guided_moves": 39,
    "red_guided_moves": 37,
    "blue_fitness": 1.0500000000000007,
    "red_fitness": 0.9600000000000004,
    "winner": "Tie"
  },
  {
    "blue_key": 833,
    "red_key": 843,
    "rounds": 37,
    "blue_tiles": 1,
    "red_tiles": 0,
    "blue_troops": 17,
    "red_troops": 0,
    "blue_production_moves": 28,
    "red_production_moves": 11,
    "blue_attack_moves": 1,
    "red_attack_moves": 19,
    "blue_transport_moves": 8,
    "red_transport_moves": 7,
    "blue_guided_moves": 37,
    "red_guided_moves": 26,
    "blue_fitness": 1.0400000000000007,
    "red_fitness": 1.4500000000000004,
    "winner": "Blue"
  },
  {
    "blue_key": 781,
    "red_key": 792,
    "rounds": 33,
    "blue_tiles": 0,
    "red_tiles": 3,
    "blue_troops": 0,
    "red_troops": 23,
    "blue_production_moves": 3,
    "red_production_moves": 26,
    "blue_attack_moves": 30,
    "red_attack_moves": 4,
    "blue_transport_moves": 0,
    "red_transport_moves": 2,
    "blue_guided_moves": 30,
    "red_guided_moves": 6,
    "blue_fitness": 1.4400000000000004,
    "red_fitness": 0.9600000000000006,
    "winner": "Red"
  },
  {
    "blue_key": 763,
    "red_key": 773,
    "rounds": 31,
    "blue_tiles": 1,
    "red_tiles": 3,
    "blue_troops": 20,
    "red_troops": 6,
    "blue_production_moves": 19,
    "red_production_moves": 5,
    "blue_attack_moves": 6,
    "red_attack_moves": 24,
    "blue_transport_moves": 6,
    "red_transport_moves": 1,
    "blue_guided_moves": 31,
    "red_guided_moves": 27,
    "blue_fitness": 0.8700000000000006,
    "red_fitness": 0.7000000000000002,
    "winner": "Tie"
  },
  {
    "blue_key": 818,
    "red_key": 828,
    "rounds": 29,
    "blue_tiles": 4,
    "red_tiles": 4,
    "blue_troops": 15,
    "red_troops": 9,
    "blue_production_moves": 14,
    "red_production_moves": 8,
    "blue_attack_moves": 15,
    "red_attack_moves": 18,
    "blue_transport_moves": 0,
    "red_transport_moves": 3,
    "blue_guided_moves": 15,
    "red_guided_moves": 29,
    "blue_fitness": 0.7800000000000004,
    "red_fitness": 0.7500000000000003,
    "winner": "Tie"
  },
  {
    "blue_key": 702,
    "red_key": 681,
    "rounds": 26,
    "blue_tiles": 2,
    "red_tiles": 1,
    "blue_troops": 5,
    "red_troops": 2,
    "blue_production_moves": 4,
    "red_production_moves": 1,
    "blue_attack_moves": 18,
    "red_attack_moves": 24,
    "blue_transport_moves": 4,
    "red_transport_moves": 0,
    "blue_guided_moves": 26,
    "red_guided_moves": 25,
    "blue_fitness": 0.61,
    "red_fitness": 0.5100000000000001,
    "winner": "Tie"
  },
  {
    "blue_key": 710,
    "red_key": 772,
    "rounds": 26,
    "blue_tiles": 2,
    "red_tiles": 1,
    "blue_troops": 20,
    "red_troops": 20,
    "blue_production_moves": 19,
    "red_production_moves": 19,
    "blue_attack_moves": 4,
    "red_attack_moves": 4,
    "blue_transport_moves": 3,
    "red_transport_moves": 3,
    "blue_guided_moves": 26,
    "red_guided_moves": 26,
    "blue_fitness": 0.7600000000000005,
    "red_fitness": 0.7400000000000004,
    "winner": "Tie"
  },
  {
    "blue_key": 713,
    "red_key": 764,
    "rounds": 26,
    "blue_tiles": 1,
    "red_tiles": 3,
    "blue_troops": 2,
    "red_troops": 10,
    "blue_production_moves": 1,
    "red_production_moves": 9,
    "blue_attack_moves": 25,
    "red_attack_moves": 8,
    "blue_transport_moves": 0,
    "red_transport_moves": 9,
    "blue_guided_moves": 26,
    "red_guided_moves": 26,
    "blue_fitness": 0.5300000000000001,
    "red_fitness": 0.6600000000000001,
    "winner": "Tie"
  },
  {
    "blue_key": 755,
    "red_key": 765,
    "rounds": 26,
    "blue_tiles": 1,
    "red_tiles": 1,
    "blue_troops": 2,
    "red_troops": 20,
    "blue_production_moves": 1,
    "red_production_moves": 19,
    "blue_attack_moves": 25,
    "red_attack_moves": 4,
    "blue_transport_moves": 0,
    "red_transport_moves": 3,
    "blue_guided_moves": 26,
    "red_guided_moves": 26,
    "blue_fitness": 0.5300000000000001,
    "red_fitness": 0.7400000000000004,
    "winner": "Tie"
  },
  {
    "blue_key": 795,
    "red_key": 806,
    "rounds": 25,
    "blue_tiles": 1,
    "red_tiles": 2,
    "blue_troops": 20,
    "red_troops": 11,
    "blue_production_moves": 22,
    "red_production_moves": 13,
    "blue_attack_moves": 3,
    "red_attack_moves": 12,
    "blue_transport_moves": 0,
    "red_transport_moves": 0,
    "blue_guided_moves": 3,
    "red_guided_moves": 12,
    "blue_fitness": 0.7800000000000005,
    "red_fitness": 1.8800000000000001,
    "winner": "Tie"
  },
  {
    "blue_key": 826,
    "red_key": 836,
    "rounds": 24,
    "blue_tiles": 1,
    "red_tiles": 1,
    "blue_troops": 11,
    "red_troops": 19,
    "blue_production_moves": 13,
    "red_production_moves": 21,
    "blue_attack_moves": 11,
    "red_attack_moves": 3,
    "blue_transport_moves": 0,
    "red_transport_moves": 0,
    "blue_guided_moves": 11,
    "red_guided_moves": 3,
    "blue_fitness": 0.8300000000000003,
    "red_fitness": 1.1300000000000003,
    "winner": "Tie"
  },
  {
    "blue_key": 837,
    "red_key": 771,
    "rounds": 24,
    "blue_tiles": 2,
    "red_tiles": 1,
    "blue_troops": 12,
    "red_troops": 19,
    "blue_production_moves": 14,
    "red_production_moves": 21,
    "blue_attack_moves": 10,
    "red_attack_moves": 3,
    "blue_transport_moves": 0,
    "red_transport_moves": 0,
    "blue_guided_moves": 10,
    "red_guided_moves": 24,
    "blue_fitness": 0.8600000000000002,
    "red_fitness": 1.1300000000000003,
    "winner": "Tie"
  },
  {
    "blue_key": 787,
    "red_key": 690,
    "rounds": 21,
    "blue_tiles": 1,
    "red_tiles": 0,
    "blue_troops": 1,
    "red_troops": 0,
    "blue_production_moves": 3,
    "red_production_moves": 2,
    "blue_attack_moves": 18,
    "red_attack_moves": 18,
    "blue_transport_moves": 0,
    "red_transport_moves": 0,
    "blue_guided_moves": 18,
    "red_guided_moves": 19,
    "blue_fitness": 0.9000000000000001,
    "red_fitness": 1.24,
    "winner": "Blue"
  },
  {
    "blue_key": 785,
    "red_key": 796,
    "rounds": 15,
    "blue_tiles": 0,
    "red_tiles": 1,
    "blue_troops": 0,
    "red_troops": 11,
    "blue_production_moves": 2,
    "red_production_moves": 13,
    "blue_attack_moves": 13,
    "red_attack_moves": 1,
    "blue_transport_moves": 0,
    "red_transport_moves": 0,
    "blue_guided_moves": 13,
    "red_guided_moves": 1,
    "blue_fitness": 0.6200000000000001,
    "red_fitness": 0.41000000000000014,
    "winner": "Red"
  },
  {
    "blue_key": 751,
    "red_key": 762,
    "rounds": 14,
    "blue_tiles": 1,
    "red_tiles": 1,
    "blue_troops": 2,
    "red_troops": 2,
    "blue_production_moves": 1,
    "red_production_moves": 1,
    "blue_attack_moves": 13,
    "red_attack_moves": 13,
    "blue_transport_moves": 0,
    "red_transport_moves": 0,
    "blue_guided_moves": 14,
    "red_guided_moves": 14,
    "blue_fitness": 0.29,
    "red_fitness": 0.29,
    "winner": "Tie"
  },
  {
    "blue_key": 799,
    "red_key": 810,
    "rounds": 12,
    "blue_tiles": 1,
    "red_tiles": 1,
    "blue_troops": 1,
    "red_troops": 1,
    "blue_production_moves": 0,
    "red_production_moves": 0,
    "blue_attack_moves": 12,
    "red_attack_moves": 11,
    "blue_transport_moves": 0,
    "red_transport_moves": 0,
    "blue_guided_moves": 12,
    "red_guided_moves": 11,
    "blue_fitness": 0.23999999999999996,
    "red_fitness": 0.21999999999999997,
    "winner": "Tie"
  },
  {
    "blue_key": 775,
    "red_key": 785,
    "rounds": 10,
    "blue_tiles": 1,
    "red_tiles": 1,
    "blue_troops": 2,
    "red_troops": 1,
    "blue_production_moves": 1,
    "red_production_moves": 0,
    "blue_attack_moves": 9,
    "red_attack_moves": 10,
    "blue_transport_moves": 0,
    "red_transport_moves": 0,
    "blue_guided_moves": 10,
    "red_guided_moves": 10,
    "blue_fitness": 0.20999999999999996,
    "red_fitness": 0.19999999999999998,
    "winner": "Tie"
  },
  {
    "blue_key": 758,
    "red_key": 769,
    "rounds": 9,
    "blue_tiles": 1,
    "red_tiles": 1,
    "blue_troops": 1,
    "red_troops": 1,
    "blue_production_moves": 0,
    "red_production_moves": 0,
    "blue_attack_moves": 9,
    "red_attack_moves": 9,
    "blue_transport_moves": 0,
    "red_transport_moves": 0,
    "blue_guided_moves": 9,
    "red_guided_moves": 9,
    "blue_fitness": 0.18,
    "red_fitness": 0.18,
    "winner": "Tie"
  },
  {
    "blue_key": 804,
    "red_key": 815,
    "rounds": 9,
    "blue_tiles": 1,
    "red_tiles": 1,
    "blue_troops": 2,
    "red_troops": 1,
    "blue_production_moves": 1,
    "red_production_moves": 0,
    "blue_attack_moves": 8,
    "red_attack_moves": 9,
    "blue_transport_moves": 0,
    "red_transport_moves": 0,
    "blue_guided_moves": 9,
    "red_guided_moves": 9,
    "blue_fitness": 0.18999999999999997,
    "red_fitness": 0.18,
    "winner": "Tie"
  },
  {
    "blue_key": 831,
    "red_key": 841,
    "rounds": 9,
    "blue_tiles": 0,
    "red_tiles": 1,
    "blue_troops": 0,
    "red_troops": 7,
    "blue_production_moves": 0,
    "red_production_moves": 7,
    "blue_attack_moves": 9,
    "red_attack_moves": 1,
    "blue_transport_moves": 0,
    "red_transport_moves": 0,
    "blue_guided_moves": 9,
    "red_guided_moves": 1,
    "blue_fitness": 0.21000000000000002,
    "red_fitness": 0.23,
    "winner": "Red"
  },
  {
    "blue_key": 665,
    "red_key": 718,
    "rounds": 8,
    "blue_tiles": 1,
    "red_tiles": 0,
    "blue_troops": 8,
    "red_troops": 0,
    "blue_production_moves": 8,
    "red_production_moves": 0,
    "blue_attack_moves": 0,
    "red_attack_moves": 8,
    "blue_transport_moves": 0,
    "red_transport_moves": 0,
    "blue_guided_moves": 8,
    "red_guided_moves": 8,
    "blue_fitness": 0.24,
    "red_fitness": 0.19,
    "winner": "Blue"
  },
  {
    "blue_key": 750,
    "red_key": 761,
    "rounds": 8,
    "blue_tiles": 1,
    "red_tiles": 0,
    "blue_troops": 8,
    "red_troops": 0,
    "blue_production_moves": 8,
    "red_production_moves": 0,
    "blue_attack_moves": 0,
    "red_attack_moves": 8,
    "blue_transport_moves": 0,
    "red_transport_moves": 0,
    "blue_guided_moves": 8,
    "red_guided_moves": 8,
    "blue_fitness": 0.24,
    "red_fitness": 0.19,
    "winner": "Blue"
  },
  {
    "blue_key": 792,
    "red_key": 802,
    "rounds": 8,
    "blue_tiles": 1,
    "red_tiles": 1,
    "blue_troops": 1,
    "red_troops": 1,
    "blue_production_moves": 0,
    "red_production_moves": 0,
    "blue_attack_moves": 8,
    "red_attack_moves": 8,
    "blue_transport_moves": 0,
    "red_transport_moves": 0,
    "blue_guided_moves": 8,
    "red_guided_moves": 8,
    "blue_fitness": 0.16,
    "red_fitness": 0.16,
    "winner": "Tie"
  },
  {
    "blue_key": 810,
    "red_key": 820,
    "rounds": 8,
    "blue_tiles": 1,
    "red_tiles": 0,
    "blue_troops": 8,
    "red_troops": 0,
    "blue_production_moves": 8,
    "red_production_moves": 0,
    "blue_attack_moves": 0,
    "red_attack_moves": 8,
    "blue_transport_moves": 0,
    "red_transport_moves": 0,
    "blue_guided_moves": 8,
    "red_guided_moves": 8,
    "blue_fitness": 0.24,
    "red_fitness": 0.19,
    "winner": "Blue"
  },
  {
    "blue_key": 806,
    "red_key": 817,
    "rounds": 8,
    "blue_tiles": 0,
    "red_tiles": 2,
    "blue_troops": 0,
    "red_troops": 4,
    "blue_production_moves": 0,
    "red_production_moves": 4,
    "blue_attack_moves": 8,
    "red_attack_moves": 3,
    "blue_transport_moves": 0,
    "red_transport_moves": 0,
    "blue_guided_moves": 8,
    "red_guided_moves": 3,
    "blue_fitness": 0.76,
    "red_fitness": 0.22,
    "winner": "Red"
  },
  {
    "blue_key": 798,
    "red_key": 809,
    "rounds": 8,
    "blue_tiles": 1,
    "red_tiles": 1,
    "blue_troops": 2,
    "red_troops": 1,
    "blue_production_moves": 1,
    "red_production_moves": 0,
    "blue_attack_moves": 7,
    "red_attack_moves": 8,
    "blue_transport_moves": 0,
    "red_transport_moves": 0,
    "blue_guided_moves": 8,
    "red_guided_moves": 8,
    "blue_fitness": 0.16999999999999998,
    "red_fitness": 0.16,
    "winner": "Tie"
  },
  {
    "blue_key": 689,
    "red_key": 814,
    "rounds": 8,
    "blue_tiles": 1,
    "red_tiles": 1,
    "blue_troops": 2,
    "red_troops": 1,
    "blue_production_moves": 1,
    "red_production_moves": 0,
    "blue_attack_moves": 7,
    "red_attack_moves": 8,
    "blue_transport_moves": 0,
    "red_transport_moves": 0,
    "blue_guided_moves": 8,
    "red_guided_moves": 8,
    "blue_fitness": 0.16999999999999998,
    "red_fitness": 0.16,
    "winner": "Tie"
  },
  {
    "blue_key": 761,
    "red_key": 771,
    "rounds": 7,
    "blue_tiles": 0,
    "red_tiles": 1,
    "blue_troops": 0,
    "red_troops": 5,
    "blue_production_moves": 0,
    "red_production_moves": 5,
    "blue_attack_moves": 7,
    "red_attack_moves": 1,
    "blue_transport_moves": 0,
    "red_transport_moves": 0,
    "blue_guided_moves": 7,
    "red_guided_moves": 6,
    "blue_fitness": 0.17,
    "red_fitness": 0.17,
    "winner": "Red"
  },
  {
    "blue_key": 782,
    "red_key": 793,
    "rounds": 7,
    "blue_tiles": 0,
    "red_tiles": 1,
    "blue_troops": 0,
    "red_troops": 5,
    "blue_production_moves": 0,
    "red_production_moves": 5,
    "blue_attack_moves": 7,
    "red_attack_moves": 1,
    "blue_transport_moves": 0,
    "red_transport_moves": 0,
    "blue_guided_moves": 7,
    "red_guided_moves": 1,
    "blue_fitness": 0.17,
    "red_fitness": 0.17,
    "winner": "Red"
  },
  {
    "blue_key": 770,
    "red_key": 780,
    "rounds": 7,
    "blue_tiles": 0,
    "red_tiles": 1,
    "blue_troops": 0,
    "red_troops": 2,
    "blue_production_moves": 0,
    "red_production_moves": 2,
    "blue_attack_moves": 7,
    "red_attack_moves": 4,
    "blue_transport_moves": 0,
    "red_transport_moves": 1,
    "blue_guided_moves": 7,
    "red_guided_moves": 5,
    "blue_fitness": 0.14,
    "red_fitness": 0.5800000000000001,
    "winner": "Red"
  },
  {
    "blue_key": 812,
    "red_key": 822,
    "rounds": 7,
    "blue_tiles": 0,
    "red_tiles": 0,
    "blue_troops": 0,
    "red_troops": 0,
    "blue_production_moves": 0,
    "red_production_moves": 0,
    "blue_attack_moves": 7,
    "red_attack_moves": 6,
    "blue_transport_moves": 0,
    "red_transport_moves": 0,
    "blue_guided_moves": 7,
    "red_guided_moves": 6,
    "blue_fitness": 0.74,
    "red_fitness": 0.12000000000000001,
    "winner": "Tie"
  },
  {
    "blue_key": 820,
    "red_key": 830,
    "rounds": 7,
    "blue_tiles": 1,
    "red_tiles": 0,
    "blue_troops": 6,
    "red_troops": 0,
    "blue_production_moves": 6,
    "red_production_moves": 0,
    "blue_attack_moves": 1,
    "red_attack_moves": 7,
    "blue_transport_moves": 0,
    "red_transport_moves": 0,
    "blue_guided_moves": 1,
    "red_guided_moves": 7,
    "blue_fitness": 0.22,
    "red_fitness": 0.74,
    "winner": "Blue"
  },
  {
    "blue_key": 828,
    "red_key": 838,
    "rounds": 7,
    "blue_tiles": 0,
    "red_tiles": 1,
    "blue_troops": 0,
    "red_troops": 5,
    "blue_production_moves": 0,
    "red_production_moves": 5,
    "blue_attack_moves": 7,
    "red_attack_moves": 1,
    "blue_transport_moves": 0,
    "red_transport_moves": 0,
    "blue_guided_moves": 7,
    "red_guided_moves": 1,
    "blue_fitness": 0.17,
    "red_fitness": 0.17,
    "winner": "Red"
  },
  {
    "blue_key": 757,
    "red_key": 767,
    "rounds": 6,
    "blue_tiles": 0,
    "red_tiles": 1,
    "blue_troops": 0,
    "red_troops": 1,
    "blue_production_moves": 0,
    "red_production_moves": 1,
    "blue_attack_moves": 6,
    "red_attack_moves": 4,
    "blue_transport_moves": 0,
    "red_transport_moves": 0,
    "blue_guided_moves": 6,
    "red_guided_moves": 5,
    "blue_fitness": 0.15000000000000002,
    "red_fitness": 0.11000000000000001,
    "winner": "Red"
  },
  {
    "blue_key": 760,
    "red_key": 770,
    "rounds": 6,
    "blue_tiles": 0,
    "red_tiles": 1,
    "blue_troops": 0,
    "red_troops": 1,
    "blue_production_moves": 0,
    "red_production_moves": 1,
    "blue_attack_moves": 6,
    "red_attack_moves": 4,
    "blue_transport_moves": 0,
    "red_transport_moves": 0,
    "blue_guided_moves": 6,
    "red_guided_moves": 5,
    "blue_fitness": 0.15000000000000002,
    "red_fitness": 0.11000000000000001,
    "winner": "Red"
  },
  {
    "blue_key": 789,
    "red_key": 799,
    "rounds": 5,
    "blue_tiles": 1,
    "red_tiles": 0,
    "blue_troops": 1,
    "red_troops": 0,
    "blue_production_moves": 1,
    "red_production_moves": 0,
    "blue_attack_moves": 4,
    "red_attack_moves": 4,
    "blue_transport_moves": 0,
    "red_transport_moves": 0,
    "blue_guided_moves": 4,
    "red_guided_moves": 4,
    "blue_fitness": 0.73,
    "red_fitness": 0.08,
    "winner": "Blue"
  },
  {
    "blue_key": 791,
    "red_key": 697,
    "rounds": 5,
    "blue_tiles": 0,
    "red_tiles": 1,
    "blue_troops": 0,
    "red_troops": 1,
    "blue_production_moves": 0,
    "red_production_moves": 1,
    "blue_attack_moves": 5,
    "red_attack_moves": 3,
    "blue_transport_moves": 0,
    "red_transport_moves": 0,
    "blue_guided_moves": 5,
    "red_guided_moves": 4,
    "blue_fitness": 0.7,
    "red_fitness": 0.11000000000000001,
    "winner": "Red"
  },
  {
    "blue_key": 769,
    "red_key": 698,
    "rounds": 5,
    "blue_tiles": 0,
    "red_tiles": 1,
    "blue_troops": 0,
    "red_troops": 1,
    "blue_production_moves": 0,
    "red_production_moves": 1,
    "blue_attack_moves": 5,
    "red_attack_moves": 3,
    "blue_transport_moves": 0,
    "red_transport_moves": 0,
    "blue_guided_moves": 5,
    "red_guided_moves": 3,
    "blue_fitness": 0.7,
    "red_fitness": 0.11000000000000001,
    "winner": "Red"
  },
  {
    "blue_key": 809,
    "red_key": 671,
    "rounds": 4,
    "blue_tiles": 0,
    "red_tiles": 0,
    "blue_troops": 0,
    "red_troops": 0,
    "blue_production_moves": 0,
    "red_production_moves": 0,
    "blue_attack_moves": 4,
    "red_attack_moves": 4,
    "blue_transport_moves": 0,
    "red_transport_moves": 0,
    "blue_guided_moves": 4,
    "red_guided_moves": 4,
    "blue_fitness": 0.08,
    "red_fitness": 0.6799999999999999,
    "winner": "Tie"
  }
]