[
  {
    "blue_key": 744,
    "red_key": 574,
    "rounds": 5000,
    "blue_tiles": 4,
    "red_tiles": 7,
    "blue_troops": 70,
    "red_troops": 130,
    "blue_production_moves": 2049,
    "red_production_moves": 2109,
    "blue_attack_moves": 1178,
    "red_attack_moves": 248,
    "blue_transport_moves": 1773,
    "red_transport_moves": 2642,
    "blue_guided_moves": 2951,
    "red_guided_moves": 2890,
    "blue_fitness": 195.47000000000867,
    "red_fitness": 165.83000000000646,
    "winner": "Tie"
  },
  {
    "blue_key": 717,
    "red_key": 699,
    "rounds": 5000,
    "blue_tiles": 16,
    "red_tiles": 20,
    "blue_troops": 301,
    "red_troops": 390,
    "blue_production_moves": 1176,
    "red_production_moves": 1265,
    "blue_attack_moves": 267,
    "red_attack_moves": 196,
    "blue_transport_moves": 3557,
    "red_transport_moves": 3538,
    "blue_guided_moves": 3824,
    "red_guided_moves": 3751,
    "blue_fitness": 162.16000000000608,
    "red_fitness": 148.790000000002,
    "winner": "Tie"
  },
  {
    "blue_key": 587,
    "red_key": 732,
    "rounds": 5000,
    "blue_tiles": 11,
    "red_tiles": 20,
    "blue_troops": 220,
    "red_troops": 376,
    "blue_production_moves": 1103,
    "red_production_moves": 1259,
    "blue_attack_moves": 1031,
    "red_attack_moves": 262,
    "blue_transport_moves": 2866,
    "red_transport_moves": 3478,
    "blue_guided_moves": 4153,
    "red_guided_moves": 3741,
    "blue_fitness": 194.3100000000072,
    "red_fitness": 144.39000000000104,
    "winner": "Tie"
  },
  {
    "blue_key": 692,
    "red_key": 753,
    "rounds": 5000,
    "blue_tiles": 7,
    "red_tiles": 10,
    "blue_troops": 120,
    "red_troops": 170,
    "blue_production_moves": 801,
    "red_production_moves": 851,
    "blue_attack_moves": 3057,
    "red_attack_moves": 1206,
    "blue_transport_moves": 1142,
    "red_transport_moves": 2942,
    "blue_guided_moves": 4218,
    "red_guided_moves": 4323,
    "blue_fitness": 145.2700000000032,
    "red_fitness": 136.42000000000033,
    "winner": "Tie"
  },
  {
    "blue_key": 748,
    "red_key": 728,
    "rounds": 5000,
    "blue_tiles": 18,
    "red_tiles": 15,
    "blue_troops": 324,
    "red_troops": 277,
    "blue_production_moves": 1260,
    "red_production_moves": 1213,
    "blue_attack_moves": 132,
    "red_attack_moves": 260,
    "blue_transport_moves": 3608,
    "red_transport_moves": 3526,
    "blue_guided_moves": 3740,
    "red_guided_moves": 4970,
    "blue_fitness": 143.04000000000067,
    "red_fitness": 159.60000000000295,
    "winner": "Tie"
  },
  {
    "blue_key": 779,
    "red_key": 758,
    "rounds": 4708,
    "blue_tiles": 15,
    "red_tiles": 21,
    "blue_troops": 249,
    "red_troops": 418,
    "blue_production_moves": 957,
    "red_production_moves": 1126,
    "blue_attack_moves": 772,
    "red_attack_moves": 136,
    "blue_transport_moves": 2979,
    "red_transport_moves": 3445,
    "blue_guided_moves": 3884,
    "red_guided_moves": 3581,
    "blue_fitness": 212.31000000000907,
    "red_fitness": 129.7399999999974,
    "winner": "Tie"
  },
  {
    "blue_key": 587,
    "red_key": 776,
    "rounds": 4631,
    "blue_tiles": 9,
    "red_tiles": 20,
    "blue_troops": 133,
    "red_troops": 399,
    "blue_production_moves": 944,
    "red_production_moves": 1210,
    "blue_attack_moves": 1045,
    "red_attack_moves": 244,
    "blue_transport_moves": 2642,
    "red_transport_moves": 3177,
    "blue_guided_moves": 3946,
    "red_guided_moves": 3423,
    "blue_fitness": 178.81999999999536,
    "red_fitness": 150.49000000000046,
    "winner": "Tie"
  },
  {
    "blue_key": 738,
    "red_key": 651,
    "rounds": 4291,
    "blue_tiles": 12,
    "red_tiles": 7,
    "blue_troops": 229,
    "red_troops": 114,
    "blue_production_moves": 1899,
    "red_production_moves": 1784,
    "blue_attack_moves": 786,
    "red_attack_moves": 1991,
    "blue_transport_moves": 1606,
    "red_transport_moves": 516,
    "blue_guided_moves": 2392,
    "red_guided_moves": 2919,
    "blue_fitness": 280.36999999999006,
    "red_fitness": 243.3600000000071,
    "winner": "Tie"
  },
  {
    "blue_key": 785,
    "red_key": 763,
    "rounds": 3938,
    "blue_tiles": 6,
    "red_tiles": 3,
    "blue_troops": 95,
    "red_troops": 59,
    "blue_production_moves": 1670,
    "red_production_moves": 1634,
    "blue_attack_moves": 1238,
    "red_attack_moves": 674,
    "blue_transport_moves": 1030,
    "red_transport_moves": 1630,
    "blue_guided_moves": 2268,
    "red_guided_moves": 2304,
    "blue_fitness": 138.630000000002,
    "red_fitness": 234.70000000000994,
    "winner": "Tie"
  },
  {
    "blue_key": 728,
    "red_key": 708,
    "rounds": 3288,
    "blue_tiles": 16,
    "red_tiles": 20,
    "blue_troops": 310,
    "red_troops": 399,
    "blue_production_moves": 708,
    "red_production_moves": 797,
    "blue_attack_moves": 391,
    "red_attack_moves": 162,
    "blue_transport_moves": 2189,
    "red_transport_moves": 2329,
    "blue_guided_moves": 2580,
    "red_guided_moves": 2896,
    "blue_fitness": 83.87000000000089,
    "red_fitness": 102.51999999999884,
    "winner": "Tie"
  },
  {
    "blue_key": 763,
    "red_key": 743,
    "rounds": 3029,
    "blue_tiles": 1,
    "red_tiles": 31,
    "blue_troops": 2,
    "red_troops": 615,
    "blue_production_moves": 1,
    "red_production_moves": 614,
    "blue_attack_moves": 3028,
    "red_attack_moves": 38,
    "blue_transport_moves": 0,
    "red_transport_moves": 2377,
    "blue_guided_moves": 3029,
    "red_guided_moves": 2415,
    "blue_fitness": 60.590000000003876,
    "red_fitness": 67.32000000000323,
    "winner": "Tie"
  },
  {
    "blue_key": 772,
    "red_key": 751,
    "rounds": 2887,
    "blue_tiles": 33,
    "red_tiles": 2,
    "blue_troops": 644,
    "red_troops": 32,
    "blue_production_moves": 675,
    "red_production_moves": 63,
    "blue_attack_moves": 78,
    "red_attack_moves": 2749,
    "blue_transport_moves": 2134,
    "red_transport_moves": 74,
    "blue_guided_moves": 2212,
    "red_guided_moves": 2886,
    "blue_fitness": 72.55000000000237,
    "red_fitness": 58.44000000000355,
    "winner": "Tie"
  },
  {
    "blue_key": 795,
    "red_key": 773,
    "rounds": 2844,
    "blue_tiles": 21,
    "red_tiles": 15,
    "blue_troops": 419,
    "red_troops": 299,
    "blue_production_moves": 752,
    "red_production_moves": 632,
    "blue_attack_moves": 209,
    "red_attack_moves": 201,
    "blue_transport_moves": 1883,
    "red_transport_moves": 2011,
    "blue_guided_moves": 2092,
    "red_guided_moves": 2220,
    "blue_fitness": 105.13999999999929,
    "red_fitness": 99.71999999999949,
    "winner": "Tie"
  },
  {
    "blue_key": 773,
    "red_key": 752,
    "rounds": 2769,
    "blue_tiles": 26,
    "red_tiles": 10,
    "blue_troops": 519,
    "red_troops": 199,
    "blue_production_moves": 659,
    "red_production_moves": 339,
    "blue_attack_moves": 78,
    "red_attack_moves": 264,
    "blue_transport_moves": 2032,
    "red_transport_moves": 2166,
    "blue_guided_moves": 2110,
    "red_guided_moves": 2768,
    "blue_fitness": 72.54000000000131,
    "red_fitness": 83.39000000000149,
    "winner": "Tie"
  },
  {
    "blue_key": 784,
    "red_key": 667,
    "rounds": 2746,
    "blue_tiles": 12,
    "red_tiles": 23,
    "blue_troops": 239,
    "red_troops": 399,
    "blue_production_moves": 573,
    "red_production_moves": 733,
    "blue_attack_moves": 414,
    "red_attack_moves": 62,
    "blue_transport_moves": 1759,
    "red_transport_moves": 1951,
    "blue_guided_moves": 2355,
    "red_guided_moves": 2066,
    "blue_fitness": 123.6999999999974,
    "red_fitness": 65.23000000000292,
    "winner": "Tie"
  },
  {
    "blue_key": 723,
    "red_key": 620,
    "rounds": 2695,
    "blue_tiles": 21,
    "red_tiles": 15,
    "blue_troops": 419,
    "red_troops": 299,
    "blue_production_moves": 726,
    "red_production_moves": 606,
    "blue_attack_moves": 194,
    "red_attack_moves": 178,
    "blue_transport_moves": 1775,
    "red_transport_moves": 1911,
    "blue_guided_moves": 1969,
    "red_guided_moves": 2090,
    "blue_fitness": 98.41999999999926,
    "red_fitness": 94.2900000000005,
    "winner": "Tie"
  },
  {
    "blue_key": 766,
    "red_key": 746,
    "rounds": 2693,
    "blue_tiles": 21,
    "red_tiles": 15,
    "blue_troops": 419,
    "red_troops": 299,
    "blue_production_moves": 720,
    "red_production_moves": 600,
    "blue_attack_moves": 214,
    "red_attack_moves": 161,
    "blue_transport_moves": 1759,
    "red_transport_moves": 1932,
    "blue_guided_moves": 1973,
    "red_guided_moves": 2096,
    "blue_fitness": 103.67999999999958,
    "red_fitness": 88.140000000001,
    "winner": "Tie"
  },
  {
    "blue_key": 768,
    "red_key": 748,
    "rounds": 2676,
    "blue_tiles": 21,
    "red_tiles": 15,
    "blue_troops": 419,
    "red_troops": 299,
    "blue_production_moves": 700,
    "red_production_moves": 580,
    "blue_attack_moves": 200,
    "red_attack_moves": 152,
    "blue_transport_moves": 1776,
    "red_transport_moves": 1944,
    "blue_guided_moves": 1977,
    "red_guided_moves": 2096,
    "blue_fitness": 97.75999999999922,
    "red_fitness": 87.74000000000098,
    "winner": "Tie"
  },
  {
    "blue_key": 793,
    "red_key": 615,
    "rounds": 2662,
    "blue_tiles": 21,
    "red_tiles": 15,
    "blue_troops": 419,
    "red_troops": 299,
    "blue_production_moves": 707,
    "red_production_moves": 587,
    "blue_attack_moves": 194,
    "red_attack_moves": 158,
    "blue_transport_moves": 1761,
    "red_transport_moves": 1917,
    "blue_guided_moves": 1955,
    "red_guided_moves": 2075,
    "blue_fitness": 97.76999999999923,
    "red_fitness": 88.85000000000096,
    "winner": "Tie"
  },
  {
    "blue_key": 762,
    "red_key": 680,
    "rounds": 2636,
    "blue_tiles": 4,
    "red_tiles": 14,
    "blue_troops": 52,
    "red_troops": 278,
    "blue_production_moves": 552,
    "red_production_moves": 778,
    "blue_attack_moves": 642,
    "red_attack_moves": 67,
    "blue_transport_moves": 1442,
    "red_transport_moves": 1790,
    "blue_guided_moves": 2084,
    "red_guided_moves": 1860,
    "blue_fitness": 84.17000000000053,
    "red_fitness": 70.62000000000249,
    "winner": "Tie"
  },
  {
    "blue_key": 794,
    "red_key": 772,
    "rounds": 2578,
    "blue_tiles": 21,
    "red_tiles": 15,
    "blue_troops": 419,
    "red_troops": 299,
    "blue_production_moves": 686,
    "red_production_moves": 566,
    "blue_attack_moves": 180,
    "red_attack_moves": 151,
    "blue_transport_moves": 1712,
    "red_transport_moves": 1861,
    "blue_guided_moves": 1892,
    "red_guided_moves": 2012,
    "blue_fitness": 92.79999999999941,
    "red_fitness": 85.42000000000087,
    "winner": "Tie"
  },
  {
    "blue_key": 731,
    "red_key": 627,
    "rounds": 2568,
    "blue_tiles": 21,
    "red_tiles": 15,
    "blue_troops": 419,
    "red_troops": 299,
    "blue_production_moves": 682,
    "red_production_moves": 562,
    "blue_attack_moves": 182,
    "red_attack_moves": 151,
    "blue_transport_moves": 1704,
    "red_transport_moves": 1855,
    "blue_guided_moves": 1886,
    "red_guided_moves": 2006,
    "blue_fitness": 91.67999999999947,
    "red_fitness": 85.18000000000086,
    "winner": "Tie"
  },
  {
    "blue_key": 658,
    "red_key": 709,
    "rounds": 2556,
    "blue_tiles": 21,
    "red_tiles": 15,
    "blue_troops": 419,
    "red_troops": 299,
    "blue_production_moves": 680,
    "red_production_moves": 560,
    "blue_attack_moves": 176,
    "red_attack_moves": 151,
    "blue_transport_moves": 1700,
    "red_transport_moves": 1845,
    "blue_guided_moves": 1876,
    "red_guided_moves": 2304,
    "blue_fitness": 90.97999999999949,
    "red_fitness": 84.92000000000084,
    "winner": "Tie"
  },
  {
    "blue_key": 730,
    "red_key": 711,
    "rounds": 2550,
    "blue_tiles": 21,
    "red_tiles": 15,
    "blue_troops": 419,
    "red_troops": 299,
    "blue_production_moves": 679,
    "red_production_moves": 559,
    "blue_attack_moves": 173,
    "red_attack_moves": 151,
    "blue_transport_moves": 1698,
    "red_transport_moves": 1840,
    "blue_guided_moves": 1871,
    "red_guided_moves": 2332,
    "blue_fitness": 90.6299999999995,
    "red_fitness": 84.79000000000084,
    "winner": "Tie"
  },
  {
    "blue_key": 747,
    "red_key": 727,
    "rounds": 2550,
    "blue_tiles": 21,
    "red_tiles": 15,
    "blue_troops": 419,
    "red_troops": 299,
    "blue_production_moves": 679,
    "red_production_moves": 559,
    "blue_attack_moves": 173,
    "red_attack_moves": 151,
    "blue_transport_moves": 1698,
    "red_transport_moves": 1840,
    "blue_guided_moves": 1871,
    "red_guided_moves": 2013,
    "blue_fitness": 90.6299999999995,
    "red_fitness": 84.79000000000084,
    "winner": "Tie"
  },
  {
    "blue_key": 735,
    "red_key": 715,
    "rounds": 2550,
    "blue_tiles": 21,
    "red_tiles": 15,
    "blue_troops": 419,
    "red_troops": 299,
    "blue_production_moves": 679,
    "red_production_moves": 559,
    "blue_attack_moves": 173,
    "red_attack_moves": 151,
    "blue_transport_moves": 1698,
    "red_transport_moves": 1840,
    "blue_guided_moves": 1871,
    "red_guided_moves": 1991,
    "blue_fitness": 90.6299999999995,
    "red_fitness": 84.79000000000084,
    "winner": "Tie"
  },
  {
    "blue_key": 764,
    "red_key": 744,
    "rounds": 2550,
    "blue_tiles": 21,
    "red_tiles": 15,
    "blue_troops": 419,
    "red_troops": 299,
    "blue_production_moves": 679,
    "red_production_moves": 559,
    "blue_attack_moves": 173,
    "red_attack_moves": 151,
    "blue_transport_moves": 1698,
    "red_transport_moves": 1840,
    "blue_guided_moves": 1871,
    "red_guided_moves": 1991,
    "blue_fitness": 90.6299999999995,
    "red_fitness": 84.79000000000084,
    "winner": "Tie"
  },
  {
    "blue_key": 769,
    "red_key": 749,
    "rounds": 2550,
    "blue_tiles": 21,
    "red_tiles": 15,
    "blue_troops": 419,
    "red_troops": 299,
    "blue_production_moves": 679,
    "red_production_moves": 559,
    "blue_attack_moves": 173,
    "red_attack_moves": 151,
    "blue_transport_moves": 1698,
    "red_transport_moves": 1840,
    "blue_guided_moves": 1871,
    "red_guided_moves": 1991,
    "blue_fitness": 90.6299999999995,
    "red_fitness": 84.79000000000084,
    "winner": "Tie"
  },
  {
    "blue_key": 796,
    "red_key": 774,
    "rounds": 2550,
    "blue_tiles": 21,
    "red_tiles": 15,
    "blue_troops": 419,
    "red_troops": 299,
    "blue_production_moves": 679,
    "red_production_moves": 559,
    "blue_attack_moves": 173,
    "red_attack_moves": 151,
    "blue_transport_moves": 1698,
    "red_transport_moves": 1840,
    "blue_guided_moves": 1871,
    "red_guided_moves": 1991,
    "blue_fitness": 90.6299999999995,
    "red_fitness": 84.79000000000084,
    "winner": "Tie"
  },
  {
    "blue_key": 792,
    "red_key": 771,
    "rounds": 2550,
    "blue_tiles": 21,
    "red_tiles": 15,
    "blue_troops": 419,
    "red_troops": 299,
    "blue_production_moves": 679,
    "red_production_moves": 559,
    "blue_attack_moves": 173,
    "red_attack_moves": 151,
    "blue_transport_moves": 1698,
    "red_transport_moves": 1840,
    "blue_guided_moves": 1935,
    "red_guided_moves": 1991,
    "blue_fitness": 90.6299999999995,
    "red_fitness": 84.79000000000084,
    "winner": "Tie"
  },
  {
    "blue_key": 770,
    "red_key": 750,
    "rounds": 2541,
    "blue_tiles": 21,
    "red_tiles": 15,
    "blue_troops": 419,
    "red_troops": 299,
    "blue_production_moves": 677,
    "red_production_moves": 557,
    "blue_attack_moves": 171,
    "red_attack_moves": 174,
    "blue_transport_moves": 1693,
    "red_transport_moves": 1810,
    "blue_guided_moves": 1864,
    "red_guided_moves": 1986,
    "blue_fitness": 90.17999999999954,
    "red_fitness": 84.61000000000082,
    "winner": "Tie"
  },
  {
    "blue_key": 729,
    "red_key": 710,
    "rounds": 2537,
    "blue_tiles": 21,
    "red_tiles": 15,
    "blue_troops": 419,
    "red_troops": 299,
    "blue_production_moves": 677,
    "red_production_moves": 557,
    "blue_attack_moves": 173,
    "red_attack_moves": 151,
    "blue_transport_moves": 1687,
    "red_transport_moves": 1829,
    "blue_guided_moves": 1862,
    "red_guided_moves": 1983,
    "blue_fitness": 89.90999999999954,
    "red_fitness": 84.51000000000084,
    "winner": "Tie"
  },
  {
    "blue_key": 736,
    "red_key": 717,
    "rounds": 2530,
    "blue_tiles": 21,
    "red_tiles": 15,
    "blue_troops": 419,
    "red_troops": 299,
    "blue_production_moves": 674,
    "red_production_moves": 554,
    "blue_attack_moves": 168,
    "red_attack_moves": 151,
    "blue_transport_moves": 1688,
    "red_transport_moves": 1825,
    "blue_guided_moves": 1856,
    "red_guided_moves": 1976,
    "blue_fitness": 89.07999999999956,
    "red_fitness": 84.34000000000081,
    "winner": "Tie"
  },
  {
    "blue_key": 787,
    "red_key": 766,
    "rounds": 2519,
    "blue_tiles": 21,
    "red_tiles": 15,
    "blue_troops": 419,
    "red_troops": 299,
    "blue_production_moves": 678,
    "red_production_moves": 558,
    "blue_attack_moves": 172,
    "red_attack_moves": 201,
    "blue_transport_moves": 1669,
    "red_transport_moves": 1760,
    "blue_guided_moves": 1841,
    "red_guided_moves": 1970,
    "blue_fitness": 90.53999999999978,
    "red_fitness": 84.24000000000082,
    "winner": "Tie"
  },
  {
    "blue_key": 750,
    "red_key": 778,
    "rounds": 2480,
    "blue_tiles": 21,
    "red_tiles": 15,
    "blue_troops": 419,
    "red_troops": 299,
    "blue_production_moves": 671,
    "red_production_moves": 551,
    "blue_attack_moves": 167,
    "red_attack_moves": 151,
    "blue_transport_moves": 1642,
    "red_transport_moves": 1778,
    "blue_guided_moves": 2145,
    "red_guided_moves": 1929,
    "blue_fitness": 87.38999999999965,
    "red_fitness": 83.31000000000077,
    "winner": "Tie"
  },
  {
    "blue_key": 628,
    "red_key": 703,
    "rounds": 2310,
    "blue_tiles": 21,
    "red_tiles": 15,
    "blue_troops": 419,
    "red_troops": 299,
    "blue_production_moves": 639,
    "red_production_moves": 519,
    "blue_attack_moves": 133,
    "red_attack_moves": 148,
    "blue_transport_moves": 1538,
    "red_transport_moves": 1643,
    "blue_guided_moves": 1677,
    "red_guided_moves": 1791,
    "blue_fitness": 76.05999999999989,
    "red_fitness": 79.53000000000094,
    "winner": "Tie"
  },
  {
    "blue_key": 635,
    "red_key": 716,
    "rounds": 2290,
    "blue_tiles": 21,
    "red_tiles": 15,
    "blue_troops": 419,
    "red_troops": 299,
    "blue_production_moves": 614,
    "red_production_moves": 494,
    "blue_attack_moves": 132,
    "red_attack_moves": 122,
    "blue_transport_moves": 1544,
    "red_transport_moves": 1674,
    "blue_guided_moves": 1676,
    "red_guided_moves": 1958,
    "blue_fitness": 75.58999999999982,
    "red_fitness": 72.78000000000121,
    "winner": "Tie"
  },
  {
    "blue_key": 737,
    "red_key": 718,
    "rounds": 2277,
    "blue_tiles": 8,
    "red_tiles": 13,
    "blue_troops": 124,
    "red_troops": 249,
    "blue_production_moves": 469,
    "red_production_moves": 594,
    "blue_attack_moves": 576,
    "red_attack_moves": 30,
    "blue_transport_moves": 1232,
    "red_transport_moves": 1652,
    "blue_guided_moves": 1808,
    "red_guided_moves": 1682,
    "blue_fitness": 79.8400000000007,
    "red_fitness": 53.68000000000195,
    "winner": "Tie"
  },
  {
    "blue_key": 790,
    "red_key": 769,
    "rounds": 2237,
    "blue_tiles": 5,
    "red_tiles": 16,
    "blue_troops": 80,
    "red_troops": 285,
    "blue_production_moves": 446,
    "red_production_moves": 651,
    "blue_attack_moves": 735,
    "red_attack_moves": 345,
    "blue_transport_moves": 1056,
    "red_transport_moves": 1240,
    "blue_guided_moves": 1869,
    "red_guided_moves": 1693,
    "blue_fitness": 75.3300000000005,
    "red_fitness": 99.5800000000019,
    "winner": "Tie"
  },
  {
    "blue_key": 758,
    "red_key": 738,
    "rounds": 2099,
    "blue_tiles": 20,
    "red_tiles": 16,
    "blue_troops": 399,
    "red_troops": 316,
    "blue_production_moves": 567,
    "red_production_moves": 484,
    "blue_attack_moves": 131,
    "red_attack_moves": 100,
    "blue_transport_moves": 1401,
    "red_transport_moves": 1515,
    "blue_guided_moves": 1532,
    "red_guided_moves": 1638,
    "blue_fitness": 71.48000000000049,
    "red_fitness": 62.53000000000164,
    "winner": "Tie"
  },
  {
    "blue_key": 726,
    "red_key": 707,
    "rounds": 2068,
    "blue_tiles": 22,
    "red_tiles": 12,
    "blue_troops": 423,
    "red_troops": 233,
    "blue_production_moves": 668,
    "red_production_moves": 478,
    "blue_attack_moves": 155,
    "red_attack_moves": 203,
    "blue_transport_moves": 1245,
    "red_transport_moves": 1386,
    "blue_guided_moves": 1404,
    "red_guided_moves": 1590,
    "blue_fitness": 53.53000000000144,
    "red_fitness": 76.28999999999999,
    "winner": "Tie"
  },
  {
    "blue_key": 732,
    "red_key": 712,
    "rounds": 1926,
    "blue_tiles": 21,
    "red_tiles": 9,
    "blue_troops": 419,
    "red_troops": 173,
    "blue_production_moves": 522,
    "red_production_moves": 276,
    "blue_attack_moves": 112,
    "red_attack_moves": 950,
    "blue_transport_moves": 1292,
    "red_transport_moves": 700,
    "blue_guided_moves": 1404,
    "red_guided_moves": 1717,
    "blue_fitness": 63.98000000000171,
    "red_fitness": 43.160000000000075,
    "winner": "Tie"
  },
  {
    "blue_key": 777,
    "red_key": 757,
    "rounds": 1846,
    "blue_tiles": 23,
    "red_tiles": 11,
    "blue_troops": 455,
    "red_troops": 204,
    "blue_production_moves": 474,
    "red_production_moves": 223,
    "blue_attack_moves": 130,
    "red_attack_moves": 25,
    "blue_transport_moves": 1242,
    "red_transport_moves": 1597,
    "blue_guided_moves": 1726,
    "red_guided_moves": 1845,
    "blue_fitness": 43.10000000000108,
    "red_fitness": 39.36000000000064,
    "winner": "Tie"
  },
  {
    "blue_key": 727,
    "red_key": 644,
    "rounds": 1845,
    "blue_tiles": 21,
    "red_tiles": 15,
    "blue_troops": 419,
    "red_troops": 299,
    "blue_production_moves": 554,
    "red_production_moves": 434,
    "blue_attack_moves": 89,
    "red_attack_moves": 108,
    "blue_transport_moves": 1202,
    "red_transport_moves": 1303,
    "blue_guided_moves": 1299,
    "red_guided_moves": 1753,
    "blue_fitness": 55.970000000001264,
    "red_fitness": 60.20000000000078,
    "winner": "Tie"
  },
  {
    "blue_key": 776,
    "red_key": 756,
    "rounds": 1657,
    "blue_tiles": 7,
    "red_tiles": 6,
    "blue_troops": 105,
    "red_troops": 120,
    "blue_production_moves": 382,
    "red_production_moves": 397,
    "blue_attack_moves": 287,
    "red_attack_moves": 219,
    "blue_transport_moves": 988,
    "red_transport_moves": 1040,
    "blue_guided_moves": 1468,
    "red_guided_moves": 1563,
    "blue_fitness": 45.44000000000065,
    "red_fitness": 51.560000000001224,
    "winner": "Tie"
  },
  {
    "blue_key": 759,
    "red_key": 739,
    "rounds": 1647,
    "blue_tiles": 15,
    "red_tiles": 12,
    "blue_troops": 243,
    "red_troops": 199,
    "blue_production_moves": 422,
    "red_production_moves": 378,
    "blue_attack_moves": 273,
    "red_attack_moves": 185,
    "blue_transport_moves": 952,
    "red_transport_moves": 1083,
    "blue_guided_moves": 1225,
    "red_guided_moves": 1281,
    "blue_fitness": 41.54000000000047,
    "red_fitness": 55.550000000000814,
    "winner": "Tie"
  },
  {
    "blue_key": 756,
    "red_key": 736,
    "rounds": 1536,
    "blue_tiles": 15,
    "red_tiles": 0,
    "blue_troops": 279,
    "red_troops": 0,
    "blue_production_moves": 512,
    "red_production_moves": 233,
    "blue_attack_moves": 25,
    "red_attack_moves": 788,
    "blue_transport_moves": 999,
    "red_transport_moves": 515,
    "blue_guided_moves": 1024,
    "red_guided_moves": 1321,
    "blue_fitness": 36.2000000000003,
    "red_fitness": 47.519999999999946,
    "winner": "Blue"
  },
  {
    "blue_key": 765,
    "red_key": 745,
    "rounds": 1448,
    "blue_tiles": 20,
    "red_tiles": 6,
    "blue_troops": 393,
    "red_troops": 93,
    "blue_production_moves": 404,
    "red_production_moves": 104,
    "blue_attack_moves": 29,
    "red_attack_moves": 637,
    "blue_transport_moves": 1015,
    "red_transport_moves": 707,
    "blue_guided_moves": 1044,
    "red_guided_moves": 1445,
    "blue_fitness": 34.230000000000004,
    "red_fitness": 32.48999999999987,
    "winner": "Tie"
  },
  {
    "blue_key": 733,
    "red_key": 713,
    "rounds": 1438,
    "blue_tiles": 20,
    "red_tiles": 16,
    "blue_troops": 399,
    "red_troops": 300,
    "blue_production_moves": 401,
    "red_production_moves": 302,
    "blue_attack_moves": 30,
    "red_attack_moves": 168,
    "blue_transport_moves": 1007,
    "red_transport_moves": 967,
    "blue_guided_moves": 1037,
    "red_guided_moves": 1295,
    "blue_fitness": 34.37999999999986,
    "red_fitness": 33.539999999999765,
    "winner": "Tie"
  },
  {
    "blue_key": 755,
    "red_key": 735,
    "rounds": 1386,
    "blue_tiles": 14,
    "red_tiles": 0,
    "blue_troops": 258,
    "red_troops": 0,
    "blue_production_moves": 462,
    "red_production_moves": 204,
    "blue_attack_moves": 30,
    "red_attack_moves": 949,
    "blue_transport_moves": 894,
    "red_transport_moves": 233,
    "blue_guided_moves": 924,
    "red_guided_moves": 1187,
    "blue_fitness": 33.98000000000003,
    "red_fitness": 43.58000000000014,
    "winner": "Blue"
  },
  {
    "blue_key": 780,
    "red_key": 759,
    "rounds": 1370,
    "blue_tiles": 9,
    "red_tiles": 27,
    "blue_troops": 179,
    "red_troops": 440,
    "blue_production_moves": 420,
    "red_production_moves": 681,
    "blue_attack_moves": 213,
    "red_attack_moves": 223,
    "blue_transport_moves": 737,
    "red_transport_moves": 465,
    "blue_guided_moves": 950,
    "red_guided_moves": 771,
    "blue_fitness": 56.70000000000137,
    "red_fitness": 58.320000000000874,
    "winner": "Tie"
  },
  {
    "blue_key": 751,
    "red_key": 731,
    "rounds": 1336,
    "blue_tiles": 17,
    "red_tiles": 12,
    "blue_troops": 316,
    "red_troops": 205,
    "blue_production_moves": 366,
    "red_production_moves": 255,
    "blue_attack_moves": 122,
    "red_attack_moves": 429,
    "blue_transport_moves": 848,
    "red_transport_moves": 651,
    "blue_guided_moves": 984,
    "red_guided_moves": 1220,
    "blue_fitness": 37.779999999999816,
    "red_fitness": 34.099999999999994,
    "winner": "Tie"
  },
  {
    "blue_key": 775,
    "red_key": 755,
    "rounds": 1332,
    "blue_tiles": 7,
    "red_tiles": 12,
    "blue_troops": 117,
    "red_troops": 227,
    "blue_production_moves": 249,
    "red_production_moves": 359,
    "blue_attack_moves": 601,
    "red_attack_moves": 89,
    "blue_transport_moves": 482,
    "red_transport_moves": 883,
    "blue_guided_moves": 1083,
    "red_guided_moves": 1329,
    "blue_fitness": 39.68000000000034,
    "red_fitness": 33.700000000000024,
    "winner": "Tie"
  },
  {
    "blue_key": 757,
    "red_key": 737,
    "rounds": 1217,
    "blue_tiles": 14,
    "red_tiles": 0,
    "blue_troops": 266,
    "red_troops": 0,
    "blue_production_moves": 444,
    "red_production_moves": 178,
    "blue_attack_moves": 31,
    "red_attack_moves": 632,
    "blue_transport_moves": 742,
    "red_transport_moves": 407,
    "blue_guided_moves": 774,
    "red_guided_moves": 1041,
    "blue_fitness": 29.079999999999828,
    "red_fitness": 39.03999999999987,
    "winner": "Blue"
  },
  {
    "blue_key": 682,
    "red_key": 765,
    "rounds": 1196,
    "blue_tiles": 17,
    "red_tiles": 15,
    "blue_troops": 335,
    "red_troops": 287,
    "blue_production_moves": 350,
    "red_production_moves": 302,
    "blue_attack_moves": 23,
    "red_attack_moves": 40,
    "blue_transport_moves": 823,
    "red_transport_moves": 853,
    "blue_guided_moves": 846,
    "red_guided_moves": 893,
    "blue_fitness": 27.739999999999757,
    "red_fitness": 30.54999999999972,
    "winner": "Tie"
  },
  {
    "blue_key": 791,
    "red_key": 770,
    "rounds": 1188,
    "blue_tiles": 18,
    "red_tiles": 15,
    "blue_troops": 341,
    "red_troops": 294,
    "blue_production_moves": 348,
    "red_production_moves": 301,
    "blue_attack_moves": 24,
    "red_attack_moves": 33,
    "blue_transport_moves": 816,
    "red_transport_moves": 854,
    "blue_guided_moves": 840,
    "red_guided_moves": 888,
    "blue_fitness": 27.579999999999757,
    "red_fitness": 28.469999999999732,
    "winner": "Tie"
  },
  {
    "blue_key": 749,
    "red_key": 729,
    "rounds": 1083,
    "blue_tiles": 9,
    "red_tiles": 11,
    "blue_troops": 143,
    "red_troops": 203,
    "blue_production_moves": 244,
    "red_production_moves": 304,
    "blue_attack_moves": 316,
    "red_attack_moves": 18,
    "blue_transport_moves": 523,
    "red_transport_moves": 760,
    "blue_guided_moves": 886,
    "red_guided_moves": 778,
    "blue_fitness": 35.44999999999984,
    "red_fitness": 24.87999999999979,
    "winner": "Tie"
  },
  {
    "blue_key": 750,
    "red_key": 730,
    "rounds": 1040,
    "blue_tiles": 8,
    "red_tiles": 8,
    "blue_troops": 154,
    "red_troops": 139,
    "blue_production_moves": 274,
    "red_production_moves": 259,
    "blue_attack_moves": 147,
    "red_attack_moves": 167,
    "blue_transport_moves": 619,
    "red_transport_moves": 614,
    "blue_guided_moves": 766,
    "red_guided_moves": 907,
    "blue_fitness": 38.61999999999984,
    "red_fitness": 33.590000000000074,
    "winner": "Tie"
  },
  {
    "blue_key": 739,
    "red_key": 719,
    "rounds": 934,
    "blue_tiles": 9,
    "red_tiles": 0,
    "blue_troops": 168,
    "red_troops": 0,
    "blue_production_moves": 368,
    "red_production_moves": 200,
    "blue_attack_moves": 18,
    "red_attack_moves": 672,
    "blue_transport_moves": 548,
    "red_transport_moves": 62,
    "blue_guided_moves": 566,
    "red_guided_moves": 781,
    "blue_fitness": 22.969999999999853,
    "red_fitness": 34.95999999999988,
    "winner": "Blue"
  },
  {
    "blue_key": 761,
    "red_key": 741,
    "rounds": 924,
    "blue_tiles": 22,
    "red_tiles": 7,
    "blue_troops": 300,
    "red_troops": 128,
    "blue_production_moves": 413,
    "red_production_moves": 241,
    "blue_attack_moves": 90,
    "red_attack_moves": 261,
    "blue_transport_moves": 421,
    "red_transport_moves": 421,
    "blue_guided_moves": 572,
    "red_guided_moves": 682,
    "blue_fitness": 28.949999999999925,
    "red_fitness": 39.480000000000224,
    "winner": "Tie"
  },
  {
    "blue_key": 720,
    "red_key": 599,
    "rounds": 759,
    "blue_tiles": 9,
    "red_tiles": 19,
    "blue_troops": 179,
    "red_troops": 271,
    "blue_production_moves": 275,
    "red_production_moves": 367,
    "blue_attack_moves": 54,
    "red_attack_moves": 203,
    "blue_transport_moves": 430,
    "red_transport_moves": 188,
    "blue_guided_moves": 559,
    "red_guided_moves": 440,
    "blue_fitness": 26.859999999999786,
    "red_fitness": 28.379999999999885,
    "winner": "Tie"
  },
  {
    "blue_key": 716,
    "red_key": 557,
    "rounds": 638,
    "blue_tiles": 16,
    "red_tiles": 9,
    "blue_troops": 116,
    "red_troops": 155,
    "blue_production_moves": 121,
    "red_production_moves": 160,
    "blue_attack_moves": 88,
    "red_attack_moves": 16,
    "blue_transport_moves": 429,
    "red_transport_moves": 461,
    "blue_guided_moves": 561,
    "red_guided_moves": 482,
    "blue_fitness": 15.939999999999808,
    "red_fitness": 14.499999999999817,
    "winner": "Tie"
  },
  {
    "blue_key": 719,
    "red_key": 701,
    "rounds": 630,
    "blue_tiles": 0,
    "red_tiles": 15,
    "blue_troops": 0,
    "red_troops": 169,
    "blue_production_moves": 95,
    "red_production_moves": 264,
    "blue_attack_moves": 349,
    "red_attack_moves": 85,
    "blue_transport_moves": 186,
    "red_transport_moves": 280,
    "blue_guided_moves": 555,
    "red_guided_moves": 383,
    "blue_fitness": 24.32999999999988,
    "red_fitness": 17.41999999999983,
    "winner": "Red"
  },
  {
    "blue_key": 722,
    "red_key": 704,
    "rounds": 594,
    "blue_tiles": 7,
    "red_tiles": 16,
    "blue_troops": 139,
    "red_troops": 176,
    "blue_production_moves": 251,
    "red_production_moves": 288,
    "blue_attack_moves": 27,
    "red_attack_moves": 213,
    "blue_transport_moves": 316,
    "red_transport_moves": 92,
    "blue_guided_moves": 343,
    "red_guided_moves": 327,
    "blue_fitness": 18.33999999999987,
    "red_fitness": 32.499999999999815,
    "winner": "Tie"
  },
  {
    "blue_key": 746,
    "red_key": 726,
    "rounds": 570,
    "blue_tiles": 6,
    "red_tiles": 10,
    "blue_troops": 119,
    "red_troops": 78,
    "blue_production_moves": 342,
    "red_production_moves": 301,
    "blue_attack_moves": 13,
    "red_attack_moves": 245,
    "blue_transport_moves": 215,
    "red_transport_moves": 24,
    "blue_guided_moves": 228,
    "red_guided_moves": 508,
    "blue_fitness": 15.139999999999848,
    "red_fitness": 63.65000000000033,
    "winner": "Tie"
  },
  {
    "blue_key": 725,
    "red_key": 706,
    "rounds": 450,
    "blue_tiles": 18,
    "red_tiles": 9,
    "blue_troops": 168,
    "red_troops": 155,
    "blue_production_moves": 235,
    "red_production_moves": 222,
    "blue_attack_moves": 195,
    "red_attack_moves": 49,
    "blue_transport_moves": 20,
    "red_transport_moves": 179,
    "blue_guided_moves": 268,
    "red_guided_moves": 235,
    "blue_fitness": 23.659999999999997,
    "red_fitness": 16.2799999999999,
    "winner": "Tie"
  },
  {
    "blue_key": 782,
    "red_key": 761,
    "rounds": 436,
    "blue_tiles": 2,
    "red_tiles": 14,
    "blue_troops": 4,
    "red_troops": 144,
    "blue_production_moves": 77,
    "red_production_moves": 217,
    "blue_attack_moves": 350,
    "red_attack_moves": 120,
    "blue_transport_moves": 9,
    "red_transport_moves": 98,
    "blue_guided_moves": 359,
    "red_guided_moves": 253,
    "blue_fitness": 19.109999999999893,
    "red_fitness": 16.359999999999875,
    "winner": "Tie"
  },
  {
    "blue_key": 778,
    "red_key": 640,
    "rounds": 421,
    "blue_tiles": 2,
    "red_tiles": 5,
    "blue_troops": 28,
    "red_troops": 81,
    "blue_production_moves": 103,
    "red_production_moves": 156,
    "blue_attack_moves": 264,
    "red_attack_moves": 12,
    "blue_transport_moves": 54,
    "red_transport_moves": 252,
    "blue_guided_moves": 318,
    "red_guided_moves": 264,
    "blue_fitness": 13.5099999999999,
    "red_fitness": 10.039999999999916,
    "winner": "Tie"
  },
  {
    "blue_key": 665,
    "red_key": 742,
    "rounds": 418,
    "blue_tiles": 6,
    "red_tiles": 14,
    "blue_troops": 103,
    "red_troops": 81,
    "blue_production_moves": 232,
    "red_production_moves": 210,
    "blue_attack_moves": 12,
    "red_attack_moves": 203,
    "blue_transport_moves": 174,
    "red_transport_moves": 5,
    "blue_guided_moves": 186,
    "red_guided_moves": 361,
    "blue_fitness": 10.77999999999993,
    "red_fitness": 35.07000000000004,
    "winner": "Tie"
  },
  {
    "blue_key": 647,
    "red_key": 723,
    "rounds": 399,
    "blue_tiles": 8,
    "red_tiles": 11,
    "blue_troops": 143,
    "red_troops": 128,
    "blue_production_moves": 145,
    "red_production_moves": 130,
    "blue_attack_moves": 14,
    "red_attack_moves": 27,
    "blue_transport_moves": 240,
    "red_transport_moves": 241,
    "blue_guided_moves": 254,
    "red_guided_moves": 271,
    "blue_fitness": 9.569999999999915,
    "red_fitness": 10.119999999999925,
    "winner": "Tie"
  },
  {
    "blue_key": 752,
    "red_key": 733,
    "rounds": 338,
    "blue_tiles": 14,
    "red_tiles": 4,
    "blue_troops": 130,
    "red_troops": 68,
    "blue_production_moves": 133,
    "red_production_moves": 71,
    "blue_attack_moves": 39,
    "red_attack_moves": 188,
    "blue_transport_moves": 166,
    "red_transport_moves": 78,
    "blue_guided_moves": 215,
    "red_guided_moves": 278,
    "blue_fitness": 9.22999999999996,
    "red_fitness": 7.549999999999965,
    "winner": "Tie"
  },
  {
    "blue_key": 753,
    "red_key": 653,
    "rounds": 323,
    "blue_tiles": 7,
    "red_tiles": 5,
    "blue_troops": 81,
    "red_troops": 93,
    "blue_production_moves": 120,
    "red_production_moves": 132,
    "blue_attack_moves": 74,
    "red_attack_moves": 12,
    "blue_transport_moves": 129,
    "red_transport_moves": 179,
    "blue_guided_moves": 206,
    "red_guided_moves": 191,
    "blue_fitness": 15.819999999999949,
    "red_fitness": 7.859999999999973,
    "winner": "Tie"
  },
  {
    "blue_key": 639,
    "red_key": 526,
    "rounds": 283,
    "blue_tiles": 9,
    "red_tiles": 5,
    "blue_troops": 117,
    "red_troops": 94,
    "blue_production_moves": 116,
    "red_production_moves": 93,
    "blue_attack_moves": 80,
    "red_attack_moves": 20,
    "blue_transport_moves": 87,
    "red_transport_moves": 170,
    "blue_guided_moves": 168,
    "red_guided_moves": 282,
    "blue_fitness": 6.989999999999972,
    "red_fitness": 6.749999999999966,
    "winner": "Tie"
  },
  {
    "blue_key": 741,
    "red_key": 721,
    "rounds": 268,
    "blue_tiles": 4,
    "red_tiles": 0,
    "blue_troops": 66,
    "red_troops": 0,
    "blue_production_moves": 148,
    "red_production_moves": 82,
    "blue_attack_moves": 20,
    "red_attack_moves": 179,
    "blue_transport_moves": 100,
    "red_transport_moves": 7,
    "blue_guided_moves": 120,
    "red_guided_moves": 211,
    "blue_fitness": 9.439999999999959,
    "red_fitness": 18.279999999999983,
    "winner": "Blue"
  },
  {
    "blue_key": 534,
    "red_key": 625,
    "rounds": 173,
    "blue_tiles": 4,
    "red_tiles": 13,
    "blue_troops": 72,
    "red_troops": 119,
    "blue_production_moves": 74,
    "red_production_moves": 121,
    "blue_attack_moves": 46,
    "red_attack_moves": 39,
    "blue_transport_moves": 53,
    "red_transport_moves": 12,
    "blue_guided_moves": 157,
    "red_guided_moves": 90,
    "blue_fitness": 4.259999999999995,
    "red_fitness": 5.550000000000001,
    "winner": "Tie"
  },
  {
    "blue_key": 771,
    "red_key": 669,
    "rounds": 153,
    "blue_tiles": 5,
    "red_tiles": 3,
    "blue_troops": 74,
    "red_troops": 42,
    "blue_production_moves": 76,
    "red_production_moves": 44,
    "blue_attack_moves": 20,
    "red_attack_moves": 46,
    "blue_transport_moves": 57,
    "red_transport_moves": 62,
    "blue_guided_moves": 119,
    "red_guided_moves": 142,
    "blue_fitness": 4.559999999999997,
    "red_fitness": 3.879999999999995,
    "winner": "Tie"
  },
  {
    "blue_key": 718,
    "red_key": 700,
    "rounds": 139,
    "blue_tiles": 0,
    "red_tiles": 3,
    "blue_troops": 0,
    "red_troops": 50,
    "blue_production_moves": 18,
    "red_production_moves": 68,
    "blue_attack_moves": 100,
    "red_attack_moves": 11,
    "blue_transport_moves": 21,
    "red_transport_moves": 59,
    "blue_guided_moves": 122,
    "red_guided_moves": 70,
    "blue_fitness": 4.08,
    "red_fitness": 3.889999999999997,
    "winner": "Red"
  },
  {
    "blue_key": 712,
    "red_key": 280,
    "rounds": 81,
    "blue_tiles": 6,
    "red_tiles": 7,
    "blue_troops": 44,
    "red_troops": 44,
    "blue_production_moves": 43,
    "red_production_moves": 43,
    "blue_attack_moves": 20,
    "red_attack_moves": 37,
    "blue_transport_moves": 18,
    "red_transport_moves": 0,
    "blue_guided_moves": 38,
    "red_guided_moves": 39,
    "blue_fitness": 2.1500000000000017,
    "red_fitness": 2.1500000000000012,
    "winner": "Tie"
  },
  {
    "blue_key": 781,
    "red_key": 760,
    "rounds": 58,
    "blue_tiles": 3,
    "red_tiles": 0,
    "blue_troops": 29,
    "red_troops": 0,
    "blue_production_moves": 40,
    "red_production_moves": 11,
    "blue_attack_moves": 9,
    "red_attack_moves": 43,
    "blue_transport_moves": 9,
    "red_transport_moves": 4,
    "blue_guided_moves": 18,
    "red_guided_moves": 58,
    "blue_fitness": 1.6000000000000012,
    "red_fitness": 3.7300000000000013,
    "winner": "Blue"
  },
  {
    "blue_key": 721,
    "red_key": 702,
    "rounds": 45,
    "blue_tiles": 1,
    "red_tiles": 6,
    "blue_troops": 20,
    "red_troops": 12,
    "blue_production_moves": 21,
    "red_production_moves": 13,
    "blue_attack_moves": 13,
    "red_attack_moves": 32,
    "blue_transport_moves": 11,
    "red_transport_moves": 0,
    "blue_guided_moves": 45,
    "red_guided_moves": 37,
    "blue_fitness": 1.8500000000000008,
    "red_fitness": 1.1500000000000006,
    "winner": "Tie"
  },
  {
    "blue_key": 711,
    "red_key": 694,
    "rounds": 33,
    "blue_tiles": 1,
    "red_tiles": 1,
    "blue_troops": 4,
    "red_troops": 20,
    "blue_production_moves": 3,
    "red_production_moves": 19,
    "blue_attack_moves": 28,
    "red_attack_moves": 11,
    "blue_transport_moves": 2,
    "red_transport_moves": 3,
    "blue_guided_moves": 30,
    "red_guided_moves": 33,
    "blue_fitness": 0.7100000000000003,
    "red_fitness": 0.8800000000000006,
    "winner": "Tie"
  },
  {
    "blue_key": 740,
    "red_key": 720,
    "rounds": 32,
    "blue_tiles": 2,
    "red_tiles": 2,
    "blue_troops": 21,
    "red_troops": 2,
    "blue_production_moves": 20,
    "red_production_moves": 1,
    "blue_attack_moves": 9,
    "red_attack_moves": 31,
    "blue_transport_moves": 3,
    "red_transport_moves": 0,
    "blue_guided_moves": 32,
    "red_guided_moves": 32,
    "blue_fitness": 0.8900000000000006,
    "red_fitness": 0.6700000000000003,
    "winner": "Tie"
  },
  {
    "blue_key": 743,
    "red_key": 724,
    "rounds": 27,
    "blue_tiles": 1,
    "red_tiles": 0,
    "blue_troops": 18,
    "red_troops": 0,
    "blue_production_moves": 20,
    "red_production_moves": 2,
    "blue_attack_moves": 7,
    "red_attack_moves": 25,
    "blue_transport_moves": 0,
    "red_transport_moves": 0,
    "blue_guided_moves": 7,
    "red_guided_moves": 27,
    "blue_fitness": 0.7400000000000004,
    "red_fitness": 0.6900000000000003,
    "winner": "Blue"
  },
  {
    "blue_key": 535,
    "red_key": 289,
    "rounds": 25,
    "blue_tiles": 1,
    "red_tiles": 2,
    "blue_troops": 20,
    "red_troops": 5,
    "blue_production_moves": 19,
    "red_production_moves": 4,
    "blue_attack_moves": 3,
    "red_attack_moves": 11,
    "blue_transport_moves": 3,
    "red_transport_moves": 9,
    "blue_guided_moves": 25,
    "red_guided_moves": 24,
    "blue_fitness": 0.7200000000000004,
    "red_fitness": 0.6300000000000001,
    "winner": "Tie"
  },
  {
    "blue_key": 654,
    "red_key": 698,
    "rounds": 18,
    "blue_tiles": 1,
    "red_tiles": 1,
    "blue_troops": 1,
    "red_troops": 1,
    "blue_production_moves": 0,
    "red_production_moves": 0,
    "blue_attack_moves": 18,
    "red_attack_moves": 17,
    "blue_transport_moves": 0,
    "red_transport_moves": 0,
    "blue_guided_moves": 18,
    "red_guided_moves": 17,
    "blue_fitness": 0.36000000000000004,
    "red_fitness": 0.34,
    "winner": "Tie"
  },
  {
    "blue_key": 734,
    "red_key": 714,
    "rounds": 14,
    "blue_tiles": 1,
    "red_tiles": 1,
    "blue_troops": 1,
    "red_troops": 1,
    "blue_production_moves": 0,
    "red_production_moves": 0,
    "blue_attack_moves": 14,
    "red_attack_moves": 13,
    "blue_transport_moves": 0,
    "red_transport_moves": 0,
    "blue_guided_moves": 14,
    "red_guided_moves": 13,
    "blue_fitness": 0.27999999999999997,
    "red_fitness": 0.25999999999999995,
    "winner": "Tie"
  },
  {
    "blue_key": 715,
    "red_key": 697,
    "rounds": 9,
    "blue_tiles": 0,
    "red_tiles": 0,
    "blue_troops": 0,
    "red_troops": 0,
    "blue_production_moves": 0,
    "red_production_moves": 0,
    "blue_attack_moves": 9,
    "red_attack_moves": 8,
    "blue_transport_moves": 0,
    "red_transport_moves": 0,
    "blue_guided_moves": 9,
    "red_guided_moves": 8,
    "blue_fitness": 0.78,
    "red_fitness": 0.16,
    "winner": "Tie"
  },
  {
    "blue_key": 713,
    "red_key": 528,
    "rounds": 8,
    "blue_tiles": 1,
    "red_tiles": 0,
    "blue_troops": 8,
    "red_troops": 0,
    "blue_production_moves": 8,
    "red_production_moves": 0,
    "blue_attack_moves": 0,
    "red_attack_moves": 8,
    "blue_transport_moves": 0,
    "red_transport_moves": 0,
    "blue_guided_moves": 0,
    "red_guided_moves": 8,
    "blue_fitness": 0.24,
    "red_fitness": 0.19,
    "winner": "Blue"
  },
  {
    "blue_key": 714,
    "red_key": 696,
    "rounds": 8,
    "blue_tiles": 1,
    "red_tiles": 0,
    "blue_troops": 8,
    "red_troops": 0,
    "blue_production_moves": 8,
    "red_production_moves": 0,
    "blue_attack_moves": 0,
    "red_attack_moves": 8,
    "blue_transport_moves": 0,
    "red_transport_moves": 0,
    "blue_guided_moves": 0,
    "red_guided_moves": 8,
    "blue_fitness": 0.24,
    "red_fitness": 0.19,
    "winner": "Blue"
  },
  {
    "blue_key": 710,
    "red_key": 693,
    "rounds": 8,
    "blue_tiles": 1,
    "red_tiles": 0,
    "blue_troops": 8,
    "red_troops": 0,
    "blue_production_moves": 8,
    "red_production_moves": 0,
    "blue_attack_moves": 0,
    "red_attack_moves": 8,
    "blue_transport_moves": 0,
    "red_transport_moves": 0,
    "blue_guided_moves": 8,
    "red_guided_moves": 8,
    "blue_fitness": 0.24,
    "red_fitness": 0.19,
    "winner": "Blue"
  },
  {
    "blue_key": 648,
    "red_key": 695,
    "rounds": 8,
    "blue_tiles": 1,
    "red_tiles": 0,
    "blue_troops": 8,
    "red_troops": 0,
    "blue_production_moves": 8,
    "red_production_moves": 0,
    "blue_attack_moves": 0,
    "red_attack_moves": 8,
    "blue_transport_moves": 0,
    "red_transport_moves": 0,
    "blue_guided_moves": 0,
    "red_guided_moves": 8,
    "blue_fitness": 0.24,
    "red_fitness": 0.19,
    "winner": "Blue"
  },
  {
    "blue_key": 745,
    "red_key": 725,
    "rounds": 8,
    "blue_tiles": 1,
    "red_tiles": 0,
    "blue_troops": 6,
    "red_troops": 0,
    "blue_production_moves": 6,
    "red_production_moves": 0,
    "blue_attack_moves": 2,
    "red_attack_moves": 8,
    "blue_transport_moves": 0,
    "red_transport_moves": 0,
    "blue_guided_moves": 8,
    "red_guided_moves": 8,
    "blue_fitness": 0.22,
    "red_fitness": 0.19,
    "winner": "Blue"
  },
  {
    "blue_key": 724,
    "red_key": 705,
    "rounds": 8,
    "blue_tiles": 1,
    "red_tiles": 0,
    "blue_troops": 8,
    "red_troops": 0,
    "blue_production_moves": 8,
    "red_production_moves": 0,
    "blue_attack_moves": 0,
    "red_attack_moves": 8,
    "blue_transport_moves": 0,
    "red_transport_moves": 0,
    "blue_guided_moves": 0,
    "red_guided_moves": 8,
    "blue_fitness": 0.24,
    "red_fitness": 0.19,
    "winner": "Blue"
  },
  {
    "blue_key": 760,
    "red_key": 740,
    "rounds": 8,
    "blue_tiles": 1,
    "red_tiles": 0,
    "blue_troops": 1,
    "red_troops": 0,
    "blue_production_moves": 1,
    "red_production_moves": 0,
    "blue_attack_moves": 7,
    "red_attack_moves": 7,
    "blue_transport_moves": 0,
    "red_transport_moves": 0,
    "blue_guided_moves": 8,
    "red_guided_moves": 7,
    "blue_fitness": 0.58,
    "red_fitness": 0.14,
    "winner": "Blue"
  },
  {
    "blue_key": 774,
    "red_key": 754,
    "rounds": 8,
    "blue_tiles": 1,
    "red_tiles": 0,
    "blue_troops": 8,
    "red_troops": 0,
    "blue_production_moves": 8,
    "red_production_moves": 0,
    "blue_attack_moves": 0,
    "red_attack_moves": 8,
    "blue_transport_moves": 0,
    "red_transport_moves": 0,
    "blue_guided_moves": 0,
    "red_guided_moves": 8,
    "blue_fitness": 0.24,
    "red_fitness": 0.19,
    "winner": "Blue"
  },
  {
    "blue_key": 754,
    "red_key": 734,
    "rounds": 7,
    "blue_tiles": 0,
    "red_tiles": 1,
    "blue_troops": 0,
    "red_troops": 5,
    "blue_production_moves": 0,
    "red_production_moves": 5,
    "blue_attack_moves": 7,
    "red_attack_moves": 1,
    "blue_transport_moves": 0,
    "red_transport_moves": 0,
    "blue_guided_moves": 7,
    "red_guided_moves": 1,
    "blue_fitness": 0.17,
    "red_fitness": 0.17,
    "winner": "Red"
  },
  {
    "blue_key": 783,
    "red_key": 762,
    "rounds": 7,
    "blue_tiles": 1,
    "red_tiles": 0,
    "blue_troops": 3,
    "red_troops": 0,
    "blue_production_moves": 3,
    "red_production_moves": 0,
    "blue_attack_moves": 3,
    "red_attack_moves": 7,
    "blue_transport_moves": 1,
    "red_transport_moves": 0,
    "blue_guided_moves": 7,
    "red_guided_moves": 7,
    "blue_fitness": 0.2,
    "red_fitness": 0.74,
    "winner": "Blue"
  },
  {
    "blue_key": 788,
    "red_key": 767,
    "rounds": 7,
    "blue_tiles": 0,
    "red_tiles": 1,
    "blue_troops": 0,
    "red_troops": 1,
    "blue_production_moves": 0,
    "red_production_moves": 1,
    "blue_attack_moves": 7,
    "red_attack_moves": 5,
    "blue_transport_moves": 0,
    "red_transport_moves": 0,
    "blue_guided_moves": 7,
    "red_guided_moves": 5,
    "blue_fitness": 0.74,
    "red_fitness": 0.15,
    "winner": "Red"
  },
  {
    "blue_key": 789,
    "red_key": 768,
    "rounds": 7,
    "blue_tiles": 0,
    "red_tiles": 1,
    "blue_troops": 0,
    "red_troops": 5,
    "blue_production_moves": 0,
    "red_production_moves": 5,
    "blue_attack_moves": 7,
    "red_attack_moves": 1,
    "blue_transport_moves": 0,
    "red_transport_moves": 0,
    "blue_guided_moves": 7,
    "red_guided_moves": 1,
    "blue_fitness": 0.17,
    "red_fitness": 0.17,
    "winner": "Red"
  },
  {
    "blue_key": 797,
    "red_key": 775,
    "rounds": 7,
    "blue_tiles": 0,
    "red_tiles": 1,
    "blue_troops": 0,
    "red_troops": 3,
    "blue_production_moves": 0,
    "red_production_moves": 3,
    "blue_attack_moves": 7,
    "red_attack_moves": 3,
    "blue_transport_moves": 0,
    "red_transport_moves": 0,
    "blue_guided_moves": 7,
    "red_guided_moves": 3,
    "blue_fitness": 0.74,
    "red_fitness": 0.17,
    "winner": "Red"
  },
  {
    "blue_key": 742,
    "red_key": 722,
    "rounds": 6,
    "blue_tiles": 0,
    "red_tiles": 0,
    "blue_troops": 0,
    "red_troops": 0,
    "blue_production_moves": 0,
    "red_production_moves": 0,
    "blue_attack_moves": 6,
    "red_attack_moves": 6,
    "blue_transport_moves": 0,
    "red_transport_moves": 0,
    "blue_guided_moves": 6,
    "red_guided_moves": 6,
    "blue_fitness": 0.12000000000000001,
    "red_fitness": 0.72,
    "winner": "Tie"
  },
  {
    "blue_key": 767,
    "red_key": 747,
    "rounds": 6,
    "blue_tiles": 0,
    "red_tiles": 2,
    "blue_troops": 0,
    "red_troops": 3,
    "blue_production_moves": 0,
    "red_production_moves": 3,
    "blue_attack_moves": 6,
    "red_attack_moves": 2,
    "blue_transport_moves": 0,
    "red_transport_moves": 0,
    "blue_guided_moves": 6,
    "red_guided_moves": 2,
    "blue_fitness": 0.15000000000000002,
    "red_fitness": 0.15,
    "winner": "Red"
  },
  {
    "blue_key": 786,
    "red_key": 764,
    "rounds": 6,
    "blue_tiles": 1,
    "red_tiles": 0,
    "blue_troops": 4,
    "red_troops": 0,
    "blue_production_moves": 4,
    "red_production_moves": 0,
    "blue_attack_moves": 2,
    "red_attack_moves": 6,
    "blue_transport_moves": 0,
    "red_transport_moves": 0,
    "blue_guided_moves": 2,
    "red_guided_moves": 6,
    "blue_fitness": 0.16,
    "red_fitness": 0.15000000000000002,
    "winner": "Blue"
  },
  {
    "blue_key": 786,
    "red_key": 777,
    "rounds": 6,
    "blue_tiles": 1,
    "red_tiles": 0,
    "blue_troops": 4,
    "red_troops": 0,
    "blue_production_moves": 4,
    "red_production_moves": 0,
    "blue_attack_moves": 2,
    "red_attack_moves": 6,
    "blue_transport_moves": 0,
    "red_transport_moves": 0,
    "blue_guided_moves": 2,
    "red_guided_moves": 6,
    "blue_fitness": 0.16,
    "red_fitness": 0.15000000000000002,
    "winner": "Blue"
  }
]